Workbook
Name aire_cercle: _xlfn.LAMBDA(_xlpm.r,PI()*_xlpm.r^2)
Name ANDvalue: IF(eng_flag,"AND","ET")
Name Born_in: '50. FILTER'!$E$4:$E$23
Name CalculDesHeures: #REF!
Name City: '50. FILTER'!$G$4:$G$23
Name COGS: _xlfn.LAMBDA(_xlpm.Begin,_xlpm.End,_xlpm.Value,(_xlpm.Begin - _xlpm.End) * _xlpm.Value)
Name Createlink: _xlfn.LAMBDA(_xlpm.sheet,_xlpm.label, HYPERLINK("#'" & _xlpm.sheet & "'!A1", _xlpm.label))
Name DELTA: #REF!
Name Department: '50. FILTER'!$B$4:$B$23
Name Employee: '50. FILTER'!$C$4:$C$23
Name Employee_ID: IF(eng_flag,"ID","ID")
Name eng_flag: TRAD!$C$4=1
Name FiscalQLookupTable: {1,3;4,4;7,1;10,2}
Name FiscalQuarter: _xlfn.LAMBDA(_xlpm.Date,"Q" & LOOKUP(MONTH(_xlpm.Date), {1,3;4,4;7,1;10,2}))
Name Gender: '50. FILTER'!$F$4:$F$23
Name HX_BonusFromID: #REF!
Name HX_EmployeeID: #REF!
Name HX_SalaryRange: #REF!
Name Liste_base: '50. FILTER'!$B$4:$H$23
Name Liste_Liens_Menu: TRAD!$D$15:$D$29
Name lst_moiscourt: TRAD!$O$13:$O$24
Name lst_moislong: TRAD!$P$13:$P$24
Name lst_monthlong: TRAD!$R$13:$R$24
Name lst_monthShort: TRAD!$Q$13:$Q$24
Name MENU_CHOICE: IF(eng_flag,TRAD!$B$13:$B$29,TRAD!$C$13:$C$29)
Name Missing_txt: IF(eng_flag,"MISSING DATA ON ROW","DONNEES MANQUANTES A LA LIGNE ")
Name NotFound: IF(eng_flag,"Not found","Pas Trouvé")
Name ORvalue: IF(eng_flag,"OR","OU")
Name Q1_horiz: {"Jan","Feb","Mar"}
Name Q2h: {"avr","mai","jun"}
Name Quarter1: {"January";"February";"March"}
Name RC_des_cubes: _xlfn.LAMBDA(_xlpm.a,_xlpm.b,ROUNDUP(SQRT(_xlpm.a^3+_xlpm.b^3),0))
Name RemoveNumbersFromText: _xlfn.LAMBDA(_xlpm.text,TRIM(_xlfn.REDUCE(_xlpm.text, _xlfn.SEQUENCE(10, , 0), _xlfn.LAMBDA(_xlpm.i,_xlpm.a, SUBSTITUTE(_xlpm.i, _xlpm.a, "")))))
Name rng_Filter: '50. FILTER'!$B$4:$H$23
Name Salary: '50. FILTER'!$D$4:$D$23
Name salfilt: '50. FILTER'!$M$6:$M$13
Name ShowFormulas: _xlfn.LAMBDA(_xlpm.reference,IFERROR(_xlfn.TOCOL(ADDRESS(ROW(_xlpm.reference), COLUMN(_xlpm.reference), 4) & ": " & _xlfn.FORMULATEXT(_xlpm.reference), 2), ""))
Name SpaceBeforeCaps: _xlfn.LAMBDA(_xlpm.Text, TRIM(_xlfn.REDUCE( _xlpm.Text, CHAR(_xlfn.SEQUENCE(26, , 65)), _xlfn.LAMBDA(_xlpm.i,_xlpm.a, SUBSTITUTE(_xlpm.i, _xlpm.a, " "&_xlpm.a)))))
Name statusList: IF(eng_flag,TRAD!$P$29:$P$35,TRAD!$Q$29:$Q$35)
Name tauxTVA: '50. FILTER'!$U$17
Name total1693: #REF!
Name TradSheetLocator: TRAD!$A$39
Name Translatefct: _xlfn.LAMBDA(_xlpm.fct_index,_xlpm.Desc_flag,VLOOKUP(_xlpm.fct_index,tbl_tradfunctions[],3-eng_flag+_xlpm.Desc_flag*2))
Name TranslateMe: _xlfn.LAMBDA(_xlpm.cellref,IF(eng_flag,INDEX(TRAD!$B:$B,_xlpm.cellref),INDEX(TRAD!$C:$C,_xlpm.cellref)))
Name txt_BornIn: IF(eng_flag,"Born in","Né(e) en ")
Name txt_Country: IF(eng_flag,"Country","Pays")
Name txt_days: IF(eng_flag," days "," jours ")
Name txt_dpt: IF(eng_flag,"Department","Département")
Name txt_Employe: IF(eng_flag,"Employee","Employé")
Name txt_Genre: IF(eng_flag,"Gender","Genre")
Name txt_hours: IF(eng_flag,"Hours","Heures")
Name txt_Month_trad: IF(eng_flag," Month "," Mois ")
Name txt_Name: IF(eng_flag,"Name","Nom")
Name txt_NotFound: IF(eng_flag,"NOT FOUND","NON TROUVE")
Name txt_PA: IF(eng_flag,"Cost","Prix achat")
Name txt_Prod: IF(eng_flag,"Products","Produits")
Name txt_PU: IF(eng_flag,"Unit Price","Prix unitaire")
Name txt_Qte: IF(eng_flag,"Qty","Qté")
Name txt_Quarter: IF(eng_flag,"Q","T")
Name txt_Revenu: IF(eng_flag,"Revenue","Revenu")

Sheet TRADFUNCTIONS
A2: Index | B2: ENG | C2: FR | D2: DESCENG | E2: DESCFR
A3: 10 | B3: FILTER | C3: FILTRE | D3: Returns an array of values that meet specified conditions. | E3: Renvoie un tableau de valeurs répondant à des critères spécifiés.
A4: 20 | B4: SORT | C4: TRIER | D4: Sorts the contents of an array or range. | E4: Trie le contenu d'un tableau ou d'une plage de cellules.
A5: 30 | B5: SORTBY | C5: TRIERPAR | D5: Sorts an array based on the values in a corresponding array. | E5: Trie un tableau en fonction des valeurs d'un tableau correspondant.
A6: 40 | B6: UNIQUE | C6: UNIQUE | D6: Returns unique values from a range or array. | E6: Renvoie des valeurs uniques à partir d'une plage ou d'un tableau.
A7: 50 | B7: SEQUENCE | C7: SEQUENCE | D7: Generates a sequence of numbers in an array. | E7: Génère une séquence de nombres sous forme de tableau.
A8: 60 | B8: RANDARRAY | C8: TABLEAU.ALEA | D8: Returns an array of random numbers. | E8: Renvoie un tableau de nombres aléatoires.
A9: 70 | B9: ARRAYTOTEXT | C9: TABLEAU.EN.TEXTE | D9: Converts an array to a text string (two formats available). | E9: Convertit un tableau en une chaîne de texte (deux formats possibles).
A10: 80 | B10: EXPAND | C10: ETENDRE | D10: Expands an array to a specified size by adding blank cells or values. | E10: Étend un tableau à une taille spécifiée en ajoutant des cellules vides ou des valeurs.
A11: 90 | B11: TOCOL | C11: DANSCOL | D11: Transforms a range or array into a single column. | E11: Transforme une plage ou un tableau en une seule colonne.
A12: 100 | B12: TOROW | C12: DANSLIGNE | D12: Transforms a range or array into a single row. | E12: Transforme une plage ou un tableau en une seule ligne.
A13: 110 | B13: WRAPCOLS | C13: ORGA.COLS | D13: Arranges values from a single column into multiple columns. | E13: Réorganise des valeurs d'une colonne unique en plusieurs colonnes.
A14: 120 | B14: WRAPROWS | C14: ORGA.LIGNES | D14: Arranges values from a single row into multiple rows. | E14: Réorganise des valeurs d'une ligne unique en plusieurs lignes.
... A100: 980 | B100: PIVOTBY | C100: PIVOTER.PAR | D100: create a summary of your data via a formula PIVOTBY(row_fields,col_fields,values,function,[field_headers],[row_total_depth],[row_sort_order],[col_total_depth],[col_sort_order],[filter_array],[relative_to]) | E100: crée un résumé de vos données via une formule. PIVOTER.PAR(row_fields,col_fields,values,function,[field_headers],[row_total_depth],[row_sort_order],[col_total_depth],[col_sort_order],[filter_array],[relative_to])

Sheet TRAD
J2: sumproduct | K2: The first condition has to be converted from boolean to number thus the *1
C3: ENGLISH | K3: La condition doit être convertie de booléen en nombre d'où le *1
C4: 1
C5: FRANCAIS
C7: ENGLISH
C8: FRANCAIS
A12: Groupe | B12: MENU ENG | C12: MENU FR | D12: Feuille lien | E12: Cellule lien | F12: Titre page | O12: lst_moiscourt | P12: lst_moislong | Q12: lst_monthShort | R12: lst_monthlong
A13: A1 | B13: List of Excel 365-Exclusive Functions | C13: Liste des nouvelles fonctions 365 | D13: A1. 365 | E13: A10 | F13: {=IF(eng_flag,Tableau4[[#This Row],[MENU ENG]],Tableau4[[#This Row],[MENU FR]])} -> List of Excel 365-Exclusive Functions | N13: 1 | O13: janv | P13: janvier | Q13: jan | R13: january
A14: A2 | B14: Array functions | C14: Fonctions matricielles | D14: A2. ARRAY | E14: A10 | F14: {=IF(eng_flag,Tableau4[[#This Row],[MENU ENG]],Tableau4[[#This Row],[MENU FR]])} -> Array functions | N14: 2 | O14: févr | P14: février | Q14: feb | R14: february
A15: 10 | B15: LOGIC | IF-AND-OR-XOR | C15: LOGIQUE | SI-ET-OU-OUX | D15: 10. LOGIC | E15: A10 | F15: {=IF(eng_flag,Tableau4[[#This Row],[MENU ENG]],Tableau4[[#This Row],[MENU FR]])} -> LOGIC | IF-AND-OR-XOR | N15: 3 | O15: mars | P15: mars | Q15: mar | R15: march
A16: 20 | B16: DATE AND TIME | C16: DATE & HEURE | D16: 20. DATE - TIME | E16: A10 | F16: {=IF(eng_flag,Tableau4[[#This Row],[MENU ENG]],Tableau4[[#This Row],[MENU FR]])} -> DATE AND TIME | N16: 4 | O16: avr | P16: avril | Q16: apr | R16: april
A17: 25 | B17: ROUND | RAND | C17: ARRONDI | ALEA | D17: 25. ROUND - RAND | E17: A10 | F17: {=IF(eng_flag,Tableau4[[#This Row],[MENU ENG]],Tableau4[[#This Row],[MENU FR]])} -> ROUND | RAND | N17: 5 | O17: mai | P17: mai | Q17: may | R17: may
A18: 30 | B18: SUMIF | SUMIFS | C18: SOMME.SI | SOMME.SI.ENS | D18: 30. COND. STATS | E18: A10 | F18: {=IF(eng_flag,Tableau4[[#This Row],[MENU ENG]],Tableau4[[#This Row],[MENU FR]])} -> SUMIF | SUMIFS | N18: 6 | O18: juin | P18: juin | Q18: jun | R18: june
A19: 30 | B19: COUNTIF(S) | SUMIF(S) | C19: NB.SI(.ENS) | SOMME.SI(.ENS) | D19: 30. COND. STATS | E19: A10 | F19: {=IF(eng_flag,Tableau4[[#This Row],[MENU ENG]],Tableau4[[#This Row],[MENU FR]])} -> COUNTIF(S) | SUMIF(S) | N19: 7 | O19: juil | P19: juillet | Q19: jul | R19: july
A20: 33 | B20: SUMPRODUCT | C20: SOMMEPRODUIT | D20: 33. SUMPRODUCT | E20: A10 | F20: {=IF(eng_flag,Tableau4[[#This Row],[MENU ENG]],Tableau4[[#This Row],[MENU FR]])} -> SUMPRODUCT | N20: 8 | O20: août | P20: août | Q20: aug | R20: august
A21: 35 | B21: ERRORS (ISEMPTY - ISNA - ISERROR) | C21: ERREURS (ESTVIDE-ESTNA-ESTERREUR) | D21: 35. ERR | E21: A10 | F21: {=IF(eng_flag,Tableau4[[#This Row],[MENU ENG]],Tableau4[[#This Row],[MENU FR]])} -> ERRORS (ISEMPTY - ISNA - ISERROR) | N21: 9 | O21: sept | P21: septembre | Q21: sep | R21: september
A22: 40 | B22: TEXT FUNCTIONS | C22: GESTION DES TEXTES | D22: 40. TEXT | E22: A10 | F22: {=IF(eng_flag,Tableau4[[#This Row],[MENU ENG]],Tableau4[[#This Row],[MENU FR]])} -> TEXT FUNCTIONS | N22: 10 | O22: oct | P22: octobre | Q22: oct | R22: october
A23: 50 | B23: FILTER | C23: FILTRE | D23: 50. FILTER | E23: A10 | F23: {=IF(eng_flag,Tableau4[[#This Row],[MENU ENG]],Tableau4[[#This Row],[MENU FR]])} -> FILTER | N23: 11 | O23: nov | P23: novembre | Q23: nov | R23: november
A24: 50 | B24: SORT | SORTBY | C24: TRIER | TRIERPAR | D24: 50. SORT | E24: A10 | F24: {=IF(eng_flag,Tableau4[[#This Row],[MENU ENG]],Tableau4[[#This Row],[MENU FR]])} -> SORT | SORTBY | N24: 12 | O24: déc | P24: décembre | Q24: dec | R24: december
A25: 60 | B25: INDEX | XMATCH | OFFSET | C25: INDEX | EQUIVX | DECALER | D25: 60. INDEX | E25: A10 | F25: {=IF(eng_flag,Tableau4[[#This Row],[MENU ENG]],Tableau4[[#This Row],[MENU FR]])} -> INDEX | XMATCH | OFFSET
A26: 60 | B26: VLOOKUP | C26: RECHERCHEV | D26: 60. VLOOKUP | E26: A10 | F26: {=IF(eng_flag,Tableau4[[#This Row],[MENU ENG]],Tableau4[[#This Row],[MENU FR]])} -> VLOOKUP
A27: 60 | B27: HLOOKUP | C27: RECHERCHEH | D27: 60. HLOOKUP | E27: A10 | F27: {=IF(eng_flag,Tableau4[[#This Row],[MENU ENG]],Tableau4[[#This Row],[MENU FR]])} -> HLOOKUP
A28: 60 | B28: XLOOKUP | C28: RECHERCHEX | D28: 60. XLOOKUP | E28: A10 | F28: {=IF(eng_flag,Tableau4[[#This Row],[MENU ENG]],Tableau4[[#This Row],[MENU FR]])} -> XLOOKUP | O28: Status column
A29: 70 | B29: FREQUENCY - RANK.EQ | C29: FREQUENCE - EQUATION.RANG | D29: 70. FREQUENCY - RANK | E29: A10 | F29: {=IF(eng_flag,Tableau4[[#This Row],[MENU ENG]],Tableau4[[#This Row],[MENU FR]])} -> FREQUENCY - RANK.EQ | O29: Active | P29: Actif(ve)
A30: 75 | B30: STDEV | C30: ECARTTYPE | D30: 75. STDEV | E30: A1 | F30: {=IF(eng_flag,Tableau4[[#This Row],[MENU ENG]],Tableau4[[#This Row],[MENU FR]])} -> STDEV | O30: Maternity leave | P30: Congé maternité
A31: 78 | B31: MATRIX HANDLING | C31: MANIPULATION DE MATRICES | D31: 78. TABLE MANIP. | E31: A3 | F31: {=IF(eng_flag,Tableau4[[#This Row],[MENU ENG]],Tableau4[[#This Row],[MENU FR]])} -> MATRIX HANDLING | O31: Pre-retirement | P31: Pré-retraite
A32: 80 | B32: GROUPBY | C32: GROUPER.PAR | D32: 80. GROUPBY | E32: A1 | F32: {=IF(eng_flag,Tableau4[[#This Row],[MENU ENG]],Tableau4[[#This Row],[MENU FR]])} -> GROUPBY | O32: Training | P32: Stagiaire
A33: 81 | B33: PIVOTBY | C33: PIVOTER.PAR | D33: 81. PIVOTBY | E33: A1 | F33: {=IF(eng_flag,Tableau4[[#This Row],[MENU ENG]],Tableau4[[#This Row],[MENU FR]])} -> PIVOTBY | P33: Sick Leave | Q33: Congé maladie
A34: 100 | B34: LET | C34: LET | D34: 80. LET | E34: A10 | F34: {=IF(eng_flag,Tableau4[[#This Row],[MENU ENG]],Tableau4[[#This Row],[MENU FR]])} -> LET | P34: Retired | Q34: Retraité
A35: 110 | B35: LAMBDA | C35: LAMBDA | D35: 90. LAMBDA | E35: A10 | F35: {=IF(eng_flag,Tableau4[[#This Row],[MENU ENG]],Tableau4[[#This Row],[MENU FR]])} -> LAMBDA | P35: Inactive | Q35: Inactif(ve)
A40: TRADUCTIONS
A41: ID | B41: Txt ENG | C41: Txt FR
A42: A2 | B42: VAT | C42: TVA
B43: PRICE | C43: PRIX
B44: List of prices with tax | C44: Liste des prix TTC
B45: Sum of rounded prices with tax | C45: Somme TTC arrondie
B46: Sum of rounded prices with tax using # | C46: Somme TTC arrondie avec #
B47: Math array formula | C47: Arithmétique matricielle
B48: Join array formula | C48: Jointure matricielle
B49: Boolean array formula | C49: Logique matricielle
B50: Find the min price for month# | C50: Trouver le prix min pour le mois#
B51: Employee cost calculation | C51: Calcul du coût d'un employé
B52: Net Salary | C52: Salaire net
B53: charges | C53: Charges sociales
B54: Pension | C54: LPP
... B100: 5. Advanced Error Handling | C100: 5. Gestion avancée des erreurs
A102: groupe | B102: ENG | C102: FR | D102: DESCENG | E102: DESCFR
A103: 1 | B103: FILTER | C103: FILTRE | D103: Returns an array of values that meet specified conditions. | E103: Renvoie un tableau de valeurs répondant à des critères spécifiés.
A104: 1 | B104: SORT | C104: TRIER | D104: Sorts the contents of an array or range. | E104: Trie le contenu d'un tableau ou d'une plage de cellules.
A105: 1 | B105: SORTBY | C105: TRIERPAR | D105: Sorts an array based on the values in a corresponding array. | E105: Trie un tableau en fonction des valeurs d'un tableau correspondant.
A106: 1 | B106: UNIQUE | C106: UNIQUE | D106: Returns unique values from a range or array. | E106: Renvoie des valeurs uniques à partir d'une plage ou d'un tableau.
A107: 1 | B107: SEQUENCE | C107: SEQUENCE | D107: Generates a sequence of numbers in an array. | E107: Génère une séquence de nombres sous forme de tableau.
A108: 1 | B108: RANDARRAY | C108: TABLEAU.ALEA | D108: Returns an array of random numbers. | E108: Renvoie un tableau de nombres aléatoires.
A109: 1 | B109: TEXTJOIN | C109: JOINDRE.TEXTE | D109: Combines text strings using a delimiter (earlier available in Excel 2016). | E109: Combine des chaînes de texte en utilisant un délimiteur (disponible depuis Excel 2016).
A110: 1 | B110: ARRAYTOTEXT | C110: TABLEAU.EN.TEXTE | D110: Converts an array to a text string (two formats available). | E110: Convertit un tableau en une chaîne de texte (deux formats possibles).
A111: 1 | B111: EXPAND | C111: ETENDRE | D111: Expands an array to a specified size by adding blank cells or values. | E111: Étend un tableau à une taille spécifiée en ajoutant des cellules vides ou des valeurs.
A112: 1 | B112: TOCOL | C112: DANSCOLONNE | D112: Transforms a range or array into a single column. | E112: Transforme une plage ou un tableau en une seule colonne.
A113: 1 | B113: TOROW | C113: DANSLIGNE | D113: Transforms a range or array into a single row. | E113: Transforme une plage ou un tableau en une seule ligne.
A114: 1 | B114: WRAPCOLS | C114: ORGA.COLS | D114: Arranges values from a single column into multiple columns. | E114: Réorganise des valeurs d'une colonne unique en plusieurs colonnes.
... A141: 6 | B141: PIVOTBY | C141: CROISER.AVEC | D141: summarizes data in a dynamic table format by grouping rows and calculating an aggregation | E141: crée un tableau croisé dynamique à partir d’un tableau source
B142: UPPER
B144: UPPER - LOWER - PROPER | C144: MAJUSCULE - MINUSCULE - NOMPROPRE
B145: SUBSTITUTE - REPLACE | C145: SUBSTITUE - REMPLACER
B146: TEXTJOIN - CONCAT | C146: JOINDRE.TEXTE - CONCAT
B147: LEFT - RIGHT -MID - TEXTBEFORE - TEXTAFTER | C147: GAUCHE - DROITE - STXT - TEXTE.AVANT - TEXTE.APRES
B148: TRIM | C148: SUPPRESPACE
B150: In order to test a lambda function, type the parameter(s) between brackets in the formula bar. | C150: Pour tester une fonction lambda, il suffit d'ajouter le(s) paramètre(s) entre parenthèses dans la barre de formule.
B152: a. LAMBDA() function that creates RC_des_cubes | C152: a. Fonction LAMBDA() pour créer RC_des_cubes
B153: b. LAMBDA() functions that creates aire_cercle | C153: b. Fonction LAMBDA() pour créer aire_cercle
B156: Sum of Sales Report Where Sales >250: | C156: Sommes des ventes > 250
B158: Regional Sales Totals with GROUPBY | C158: Totaux des ventes régionales avec GROUPER.PAR
B159: LAMBDA version | C159: Avec LAMBDA
B160: Regional % of Sales Totals | C160: % des ventes par région
... B198: Threshold | C198: Seuil
B199: Sum of positive sales
B200: Total quantities with less than 60 units per sale | C200: Totaux des ventes inferieures a 60 unites
B201: Total quantities 1 & 2 when the value is greater than 60 units per sale | C201: Ventes où les qtés 1 et 2 sont supérieures à 60
B202: Total quantities 3 & 4 when total for 1 & 2 is greater than 60 units per sale | C202: Totaux des qtés 3 et 4 lorsque les qtés 1 et 2 sont supérieures à 60
B203: Total nb of orders | C203: NB de ventes dans la plage sélectionnée
B204: Nb of orders with less than 60 units sold | C204: NB de ventes de 60 unités au max
B205: Average of totals over 230 | C205: Moyenne des totaux dépassant 230
B206: Number of rows containing 40 in the name and cost < 300 | C206: Nb de lignes où le nom contient 40 et le coût est < à 300
B207: Total number of Geforce cards sold with a unit price > 500 CHF | C207: NB total de cartes Geforce vendues avec un PU > à 500
B208: Total NB of Geforce sold with a cost between 300 & 500 CHF | C208: NB total de cartes Geforce vendues avec un Coût entre 300 et 500
B209: Total sales for products starting with 'Ge' | C209: Totaux des ventes pour les produits commençant par 'Ge'
B210: Sale | C210: Vente
B211: Company | C211: Société
... B274: Gross costs | C274: Dépenses brutes

Sheet MENU
G2: Ludovic Moreau | J2: moreau@artofnet.ch
B3: {=TranslateMe(14)} -> Array functions
B5: =HYPERLINK("#'"&TRAD!D14&"'!A1",TRAD!F14) -> Array functions
B6: =HYPERLINK("#'"&TRAD!D13&"'!A1",TRAD!F13) -> List of Excel 365-Exclusive Functions
B7: =HYPERLINK("#'"&TRAD!D20&"'!A1",TRAD!F20) -> SUMPRODUCT
B8: =HYPERLINK("#'"&TRAD!D23&"'!A1",TRAD!F23) -> FILTER
B9: =HYPERLINK("#'"&TRAD!D24&"'!A1",TRAD!F24) -> SORT | SORTBY
B10: =HYPERLINK("#'"&TRAD!D25&"'!A1",TRAD!F25) -> INDEX | XMATCH | OFFSET
B11: =HYPERLINK("#'"&TRAD!D26&"'!A1",TRAD!F26) -> VLOOKUP
B12: =HYPERLINK("#'"&TRAD!D28&"'!A1",TRAD!F28) -> XLOOKUP
B13: =HYPERLINK("#'"&TRAD!D31&"'!A1",TRAD!F31) -> MATRIX HANDLING
B14: =HYPERLINK("#'"&TRAD!D29&"'!A1",TRAD!F29) -> FREQUENCY - RANK.EQ
B21: #VALUE!
B22: Excel functions (alphabetical)
B23: Fonctions Excel (alphabétiques)

Sheet A1. 365
A1: #VALUE! | B1: #VALUE! | C1: {=TranslateMe(13)} -> List of Excel 365-Exclusive Functions
B3: {="1."&TranslateMe(247)} -> 1.Array functions
B5: FILTRE | C5: Renvoie un tableau de valeurs répondant à des critères spécifiés.
B6: TRIER | C6: Trie le contenu d'un tableau ou d'une plage de cellules.
B7: TRIERPAR | C7: Trie un tableau en fonction des valeurs d'un tableau correspondant.
B8: UNIQUE | C8: Renvoie des valeurs uniques à partir d'une plage ou d'un tableau.
B9: SEQUENCE | C9: Génère une séquence de nombres sous forme de tableau.
B10: TABLEAU.ALEA | C10: Renvoie un tableau de nombres aléatoires.
B11: JOINDRE.TEXTE | C11: Combine des chaînes de texte en utilisant un délimiteur (disponible depuis Excel 2016).
B12: TABLEAU.EN.TEXTE | C12: Convertit un tableau en une chaîne de texte (deux formats possibles).
B13: ETENDRE | C13: Étend un tableau à une taille spécifiée en ajoutant des cellules vides ou des valeurs.
B14: DANSCOLONNE | C14: Transforme une plage ou un tableau en une seule colonne.
B15: DANSLIGNE | C15: Transforme une plage ou un tableau en une seule ligne.
B16: ORGA.COLS | C16: Réorganise des valeurs d'une colonne unique en plusieurs colonnes.
... B21: ASSEMB.H | C21: Empile horizontalement des tableaux ou des plages.
B23: {="2."&TranslateMe(248)} -> 2.New search and index functions
B25: RECHERCHEX | C25: Remplace RECHERCHEV et RECHERCHEH, permet des recherches plus flexibles.
B26: EQUIVX | C26: Renvoie la position relative d'une valeur dans un tableau (remplace EQUIV).
B28: {="3."&TranslateMe(249)} -> 3.Mathematical & statistical functions
B30: LET | C30: Assigne des noms à des résultats de calcul pour les réutiliser dans une formule.
B31: LAMBDA | C31: Permet de définir des fonctions personnalisées réutilisables.
B32: BYROW | C32: Applique une fonction LAMBDA à chaque ligne d'un tableau.
B33: BYCOL | C33: Applique une fonction LAMBDA à chaque colonne d'un tableau.
B34: CREERTABLEAU | C34: Crée un tableau en fonction d'une fonction LAMBDA.
B35: CARTOGRAPHIE | C35: Applique une fonction LAMBDA élément par élément sur des tableaux.
B36: REDUCE | C36: Réduit un tableau à une valeur cumulée en appliquant une fonction LAMBDA.
B37: SCAN | C37: Renvoie les résultats intermédiaires d'une opération cumulative sur un tableau.
B38: FRACTIONNER.TEXTE | C38: Divise des chaînes de texte en tableaux à l'aide de délimiteurs.
B39: PRENDRE | C39: Renvoie un nombre spécifié de lignes ou de colonnes du début ou de la fin d'un tableau.
B40: SUPPRIMER | C40: Exclut un nombre spécifié de lignes ou de colonnes d'un tableau.
B42: {="4."&TranslateMe(250)} -> 4.AI based functions
B44: IMAGE | C44: Insère une image dans une cellule à partir d'une URL.
B45: TEXTE.APRES | C45: Extrait le texte après une sous-chaîne spécifiée.
B46: TEXTE.AVANT | C46: Extrait le texte avant une sous-chaîne spécifiée.
B47: HISTORIQUE.ACTIONS | C47: Récupère les données historiques des cours boursiers.
B48: ISOMITTED | C48: Vérifie si une valeur est omise dans une fonction LAMBDA ou personnalisée.
B50: {="5."&TranslateMe(251)} -> 5.Advanced error handling
B52: SIERREUR | C52: (Disponible précédemment mais mise à jour) Gère les erreurs et renvoie une valeur spécifiée.
B53: SI.NA | C53: Gère spécifiquement les erreurs #N/A.

Sheet A2. ARRAY
A1: #VALUE! | C1: {=TranslateMe(14)} -> Array functions | G1: {=TranslateMe(255)} -> An array formula is a formula that works on a set of values [table, matrix] and return a single result or a range of cells (array).
B2: {=TranslateMe(79)} -> Vertical list | F2: {=TranslateMe(80)} -> Horizontal list
B3: =_xlfn.FORMULATEXT(B4) -> ={1;2;3;4;5} | C3: =_xlfn.FORMULATEXT(C4) -> ={"John";"Peter";"Paul"} | F3: =_xlfn.FORMULATEXT(F4) -> ={"john"."Peter"."Paul"}
B4: {={1;2;3;4;5}} -> 1 | C4: {={"John";"Peter";"Paul"}} -> John | F4: {={"john","Peter","Paul"}} -> john | G4: Peter | H4: Paul | J4: {=TranslateMe(253)} -> \' may be replaced by '.' in an horizontal list depending on your windows regional settings
B5: 2 | C5: Peter
B6: 3 | C6: Paul | F6: {=TranslateMe(258)} -> A matrix function only resides in the top left cell of the resulting array
B7: 4 | F7: {=TranslateMe(259)} -> All other results will display the original formula grayed out (not editable).
B8: 5
B11: =_xlfn.FORMULATEXT(B12) -> =DANSLIGNE(B4#) | D11: {=Translatefct(113,1)} -> Arranges values from a single column into multiple columns.
B12: {=_xlfn.TOROW(_xlfn.ANCHORARRAY(B4))} -> 1 | C12: 2 | D12: 3 | E12: 4 | F12: 5 | H12: {=TranslateMe(257)} -> Use the '#' symbol to select all output values froma matrix function
B13: =_xlfn.FORMULATEXT(B14) -> =TRANSPOSE(B4#)
B14: {=TRANSPOSE(_xlfn.ANCHORARRAY(B4))} -> 1 | C14: 2 | D14: 3 | E14: 4 | F14: 5
B16: =_xlfn.FORMULATEXT(B17) -> ={10.2.3.4.5}
B17: {={10,2,3,4,5}} -> 10 | C17: 2 | D17: 3 | E17: 4 | F17: 5
B18: =_xlfn.FORMULATEXT(B19) -> =SOMME(B17#*{5.4.3.2.1})
B19: {=SUM(_xlfn.ANCHORARRAY(B17)*{5,4,3,2,1})} -> 80
A21: =_xlfn.FORMULATEXT(B21) -> =B17# | B21: {=_xlfn.ANCHORARRAY(B17)} -> 10 | C21: 2 | D21: 3 | E21: 4 | F21: 5
A22: =_xlfn.FORMULATEXT(B22) -> ={5.4.3.2.1} | B22: {={5,4,3,2,1}} -> 5 | C22: 4 | D22: 3 | E22: 2 | F22: 1
A23: =_xlfn.FORMULATEXT(B23) -> =B17#*{5.4.3.2.1} | B23: {=_xlfn.ANCHORARRAY(B17)*{5,4,3,2,1}} -> 50 | C23: 8 | D23: 9 | E23: 8 | F23: 5
B25: =_xlfn.FORMULATEXT(B26) -> =SOMME(B17#*{5;4;3;2;1})
B26: {=SUM(_xlfn.ANCHORARRAY(B17)*{5;4;3;2;1})} -> 360
A27: =_xlfn.FORMULATEXT(B27) -> =B17#*{5;4;3;2;1} | B27: {=_xlfn.ANCHORARRAY(B17)*{5;4;3;2;1}} -> 50 | C27: 10 | D27: 15 | E27: 20 | F27: 25
B28: 40 | C28: 8 | D28: 12 | E28: 16 | F28: 20
B29: 30 | C29: 6 | D29: 9 | E29: 12 | F29: 15
B30: 20 | C30: 4 | D30: 6 | E30: 8 | F30: 10
B31: 10 | C31: 2 | D31: 3 | E31: 4 | F31: 5
B33: =_xlfn.FORMULATEXT(B34) -> ={1;2;3}*{1.2.3} | F33: =_xlfn.FORMULATEXT(F34) -> =SOMME(B34#)
B34: {={1;2;3}*{1,2,3}} -> 1 | C34: 2 | D34: 3 | F34: =SUM(_xlfn.ANCHORARRAY(B34)) -> 36
B35: 2 | C35: 4 | D35: 6
B36: 3 | C36: 6 | D36: 9
B39: Shares | C39: 500 | D39: 300 | E39: 250 | F39: 400
B40: Price | C40: 12.5 | D40: 5.8 | E40: 14 | F40: 21.3
C41: =_xlfn.FORMULATEXT(C42) -> =C39:F39*C40:F40
B42: Totals | C42: {=C39:F39*C40:F40} -> 6250 | D42: 1740 | E42: 3500 | F42: 8520
B44: total | C44: {=SUM(C39:F39*C40:F40)} -> 20010 | D44: =_xlfn.FORMULATEXT(C44) -> =SOMME(C39:F39*C40:F40)
C45: =SUMPRODUCT(C39:F39,C40:F40) -> 20010 | D45: =_xlfn.FORMULATEXT(C45) -> =SOMMEPROD(C39:F39;C40:F40)
B47: {=TranslateMe(260)} -> Array functions can also be part of defined names.
B48: =_xlfn.FORMULATEXT(B49) -> =Quarter1 | C48: =_xlfn.FORMULATEXT(C49) -> =Q1_horiz
B49: {=Quarter1} -> January | C49: {=Q1_horiz} -> Jan | D49: Feb | E49: Mar
B50: February
B51: March
B53: {=TranslateMe(263)} -> Array manipulation
B54: DATE | C54: PROD | D54: TOTAL | F54: {=TranslateMe(42)} -> VAT | G54: 0.081 | I54: =_xlfn.FORMULATEXT(I55) -> =UNIQUE(MOIS($B$55:$B$60))
B55: 45422 | C55: Prod1 | D55: 12.56 | I55: {=_xlfn.UNIQUE(MONTH($B$55:$B$60))} -> 5
B56: 45437 | C56: Prod2 | D56: 4.22 | F56: {=TranslateMe(261)} -> Data validation usign an array function | I56: 6
B57: 45452 | C57: Prod3 | D57: 25.33 | F57: {=TranslateMe(71)} -> Month | I57: 7
B58: 45467 | C58: Prod1 | D58: 12.5 | F58: 6 | G58: 2025 | I58: =_xlfn.FORMULATEXT(I59) -> =UNIQUE(ANNEE($B$55:$B$60))
B59: 45847 | C59: Prod2 | D59: 21.66 | G59: 2024 | I59: {=_xlfn.UNIQUE(YEAR($B$55:$B$60))} -> 2024
B60: 46227 | C60: Prod1 | D60: 15.4 | G60: 2025 | I60: 2025
I61: 2026
B63: {=TranslateMe(262)} -> Array multiplication: multiply an array by a number | G63: {=TranslateMe(263)} -> Array manipulation | J63: {=TranslateMe(264)} -> Array manipulation in an IF function
B64: VAT | D64: PRICE | G64: =_xlfn.FORMULATEXT(G65) -> =TEXTE(B55:B60;"jj.mmm.aa")&" : CHF "&D55:D60 | J64: =_xlfn.FORMULATEXT(J65) -> =SI(D55:D60>$K$65;">"&$K$65;"")
B65: {=D55:D60*(100%+$G$54)} -> 13.57736 | D65: {=SUM(ROUND(D55:D60*(1+$G$54),2))} -> 99.09 | G65: {=TEXT(B55:B60,"jj.mmm.aa")&" : CHF "&D55:D60} -> 10.mai.24 : CHF 12,56 | J65: {=IF(D55:D60>$K$65,">"&$K$65,"")} | K65: 15
B66: 4.56182 | D66: =_xlfn.FORMULATEXT(D65) -> =SOMME(ARRONDI(D55:D60*(1+$G$54);2)) | G66: 25.mai.24 : CHF 4,22
B67: 27.38173 | G67: 09.juin.24 : CHF 25,33 | J67: >15
B68: 13.5125 | D68: List of prices with tax | G68: 24.juin.24 : CHF 12,5
B69: 23.41446 | D69: {=SUM(ROUND(_xlfn.ANCHORARRAY($B$65),1))} -> 99.1 | G69: 09.juil.25 : CHF 21,66 | J69: >15
B70: 16.6474 | D70: =_xlfn.FORMULATEXT(D69) -> =SOMME(ARRONDI($B$65#;1)) | G70: 24.juil.26 : CHF 15,4 | J70: >15
B72: {=TranslateMe(265)} -> 365 functions
A73: =_xlfn.FORMULATEXT(C75) -> =DATE(B75#;C74#;C74#) | C73: =_xlfn.FORMULATEXT(C74) -> =SEQUENCE(1;6)
C74: {=_xlfn.SEQUENCE(1,6)} -> 1 | D74: 2 | E74: 3 | F74: 4 | G74: 5 | H74: 6
B75: {=_xlfn.SEQUENCE(5,1,2018,1)} -> 2018 | C75: {=DATE(_xlfn.ANCHORARRAY(B75),_xlfn.ANCHORARRAY(C74),_xlfn.ANCHORARRAY(C74))} -> 43101 | D75: 43133 | E75: 43162 | F75: 43194 | G75: 43225 | H75: 43257
B76: 2019 | C76: 43466 | D76: 43498 | E76: 43527 | F76: 43559 | G76: 43590 | H76: 43622
B77: 2020 | C77: 43831 | D77: 43863 | E77: 43893 | F77: 43925 | G77: 43956 | H77: 43988
B78: 2021 | C78: 44197 | D78: 44229 | E78: 44258 | F78: 44290 | G78: 44321 | H78: 44353
B79: 2022 | C79: 44562 | D79: 44594 | E79: 44623 | F79: 44655 | G79: 44686 | H79: 44718
B80: =_xlfn.FORMULATEXT(B75) -> =SEQUENCE(5;1;2018;1)
B83: =_xlfn.FORMULATEXT(B84) -> =UNIQUE($C$55:$C$60) | D83: =_xlfn.FORMULATEXT(D84) -> =TRIER(B55:D60;2;1) | H83: =_xlfn.FORMULATEXT(H84) -> =TRIERPAR(B55:D60;C55:C60;1;D55:D60;-1)
B84: {=_xlfn.UNIQUE($C$55:$C$60)} -> Prod1 | D84: {=_xlfn._xlws.SORT(B55:D60,2,1)} -> 45422 | E84: Prod1 | F84: 12.56 | H84: {=_xlfn.SORTBY(B55:D60,C55:C60,1,D55:D60,-1)} -> 46227 | I84: Prod1 | J84: 15.4
B85: Prod2 | D85: 45467 | E85: Prod1 | F85: 12.5 | H85: 45422 | I85: Prod1 | J85: 12.56
B86: Prod3 | D86: 46227 | E86: Prod1 | F86: 15.4 | H86: 45467 | I86: Prod1 | J86: 12.5
D87: 45437 | E87: Prod2 | F87: 4.22 | H87: 45847 | I87: Prod2 | J87: 21.66
D88: 45847 | E88: Prod2 | F88: 21.66 | H88: 45437 | I88: Prod2 | J88: 4.22
D89: 45452 | E89: Prod3 | F89: 25.33 | H89: 45452 | I89: Prod3 | J89: 25.33
B92: =_xlfn.FORMULATEXT(B93) -> =SEQUENCE(2) | D92: =_xlfn.FORMULATEXT(D93) -> =GRANDE.VALEUR(D55:D60;SEQUENCE(3)) | F92: =_xlfn.FORMULATEXT(F93) -> =GRANDE.VALEUR(D55:D60;3)
B93: {=_xlfn.SEQUENCE(2)} -> 1 | D93: {=LARGE(D55:D60,_xlfn.SEQUENCE(3))} -> 25.33 | F93: =LARGE(D55:D60,3) -> 15.4
B94: 2 | D94: 21.66
D95: 15.4
B97: {=TranslateMe(267)} -> Estimated return of a capital with fixed interest | I97: =VC(taux ; npm ; vpm ; [va] ; [type])
B98: {=TranslateMe(269)} -> Periods/Interest rate | C98: {=_xlfn.SEQUENCE(1,5,0.02,0.005)} -> 0.02 | D98: 0.025 | E98: 0.03 | F98: 0.035 | G98: 0.04 | I98: taux | J98: Oui | K98: Taux d’intérêt par période (mensuel, annuel…). [support.mi...rosoft.com]
A99: {=TranslateMe(268)} -> Yearly payment | B99: {=_xlfn.SEQUENCE(6,1,10,3)} -> 10 | C99: {=ROUND(FV(_xlfn.ANCHORARRAY(C98),_xlfn.ANCHORARRAY(B99),-A100,-A102),0)} -> 170447 | D99: 176038 | E99: 181835 | F99: 187844 | G99: 194073 | I99: npm | J99: Oui | K99: Nombre total de périodes (mois, années…). [support.mi...rosoft.com]
A100: 10000 | B100: 13 | C100: 211484 | D100: 220330 | E100: 229605 | F100: 239328 | G100: 249522 | I100: vpm | J100: Oui | K100: Paiement effectué à chaque période (souvent négatif car sortie d’argent). [support.mi...rosoft.com]
A101: {=TranslateMe(266)} -> Initial capital | B101: 16 | C101: 255032 | D101: 268028 | E101: 281804 | F101: 296410 | G101: 311894 | I101: va | J101: Non | K101: Valeur actuelle (capital initial). Par défaut = 0. [support.mi...rosoft.com]
A102: 50000 | B102: 19 | C102: 301246 | D102: 319393 | E102: 338844 | F102: 359697 | G102: 382055 | I102: type | J102: Non | K102: Indique quand les paiements ont lieu : 0 = fin de période, 1 = début. [support.mi...rosoft.com]
B103: 22 | C103: 350289 | D103: 374707 | E103: 401173 | F103: 429865 | G103: 460976 | I103: VC (Valeur Capitalisée) = fonction financière utilisée pour projeter la croissance d’un capital dans le temps
B104: 25 | C104: 402333 | D104: 434275 | E104: 469282 | F104: 507661 | G104: 549751
B107: Portfolio estimation
B108: Portfolio value | C108: 1000000 | D108: 0.6 | E108: 0.4 | F108: Portfolio growth before dividends | H108: Dividends | J108: Global growth
C109: Dividends | D109: Stock A Growth | E109: Stock B Growth | F109: Stock A | G109: Stock B | H109: Stock A | I109: Stock B | J109: Stock A | K109: Stock B | L109: Total | M109: %
B110: Optimistic | C110: 0.03 | D110: 0.12 | E110: 0.1 | F110: {=$C$108*$D$108:$E$108*$D$110:$E$112} -> 72000 | G110: 40000 | H110: {=$C$108*$D$108:$E$108*$C$110:$C$112} -> 18000 | I110: 12000 | J110: {=$C$108*$D$108:$E$108*($D$110:$E$112+$C$110:$C$112)} -> 90000 | K110: 52000 | L110: {=J110:J112+K110:K112} -> 142000 | M110: {=L110:L112/$C$108} -> 0.142
B111: Normal | C111: 0.015 | D111: 0.05 | E111: 0.04 | F111: 30000 | G111: 16000 | H111: 9000 | I111: 6000 | J111: 39000 | K111: 22000 | L111: 61000 | M111: 0.061
B112: Poor | C112: 0 | D112: -0.02 | E112: 0.015 | F112: -12000 | G112: 6000 | H112: 0 | I112: 0 | J112: -12000 | K112: 6000 | L112: -6000 | M112: -0.006
E114: =_xlfn.FORMULATEXT(F110) -> =$C$108*$D$108:$E$108*$D$110:$E$112
G115: =_xlfn.FORMULATEXT(H110) -> =$C$108*$D$108:$E$108*$C$110:$C$112
I116: =_xlfn.FORMULATEXT(J110) -> =$C$108*$D$108:$E$108*($D$110:$E$112+$C$110:$C$112)

Sheet 33. SUMPRODUCT
A1: #VALUE! | C1: {=Translatefct(940,0)} -> SUMPRODUCT | G1: {=Translatefct(940,1)} -> Returns the sum of the products of corresponding ranges or arrays.
B4: {=TranslateMe(211)} -> Company | C4: {=TranslateMe(191)} -> Products | D4: {=TranslateMe(192)} -> Unit price | E4: {=TranslateMe(195)} -> Qty | F4: TOTAL
B5: Company1 | C5: HDD1 | D5: 122 | E5: 23 | F5: =D5*E5 -> 2806 | I5: {=TranslateMe(214)} -> SUMPRODUCT WITH CONDITION | M5: =_xlfn.FORMULATEXT($J$8) -> =SOMMEPROD((C5:C16=J7)*1;E5:E16)
B6: Company2 | C6: HDD2 | D6: 115 | E6: 15 | F6: =D6*E6 -> 1725
B7: Company3 | C7: HDD9 | D7: 115 | E7: 44 | F7: =D7*E7 -> 5060 | I7: {=TranslateMe(212)} -> Product | J7: Ecran2 | M7: =_xlfn.FORMULATEXT(J9) -> =SOMMEPROD((C5:C16=J7)*1;E5:E16;D5:D16)
B8: Company4 | C8: Clavier1 | D8: 185 | E8: 35 | F8: =D8*E8 -> 6475 | I8: {=TranslateMe(195)} -> Qty | J8: {=SUMPRODUCT((C5:C16=J7)*1,E5:E16)} -> 154
B9: Company5 | C9: Clavier1 | D9: 185 | E9: 26 | F9: =D9*E9 -> 4810 | I9: {=TranslateMe(210)} -> Sale | J9: {=SUMPRODUCT((C5:C16=J7)*1,E5:E16,D5:D16)} -> 7546
B10: Company1 | C10: Clavier1 | D10: 185 | E10: 17 | F10: =D10*E10 -> 3145
B11: Company5 | C11: Clavier2 | D11: 205 | E11: 18 | F11: =D11*E11 -> 3690 | I11: {=TranslateMe(215)} -> The first condition has to be converted from boolean to number thus the *1
B12: Company3 | C12: Ecran1 | D12: 115 | E12: 101 | F12: =D12*E12 -> 11615
B13: Company4 | C13: Ecran2 | D13: 49 | E13: 154 | F13: =D13*E13 -> 7546 | J13: =_xlfn.FORMULATEXT(J14) -> =C5:C16=J7 | K13: =_xlfn.FORMULATEXT(K14) -> =(C5:C16=J7)*1 | L13: =_xlfn.FORMULATEXT(L14) -> =$E$5:$E$16*$D$5:$D$16 | M13: =_xlfn.FORMULATEXT(M14) -> =(C5:C16=J7)*1*E5:E16*D5:D16
B14: Company4 | C14: Ecran3 | D14: 115 | E14: 66 | F14: =D14*E14 -> 7590 | J14: {=C5:C16=J7} -> FALSE | K14: {=(C5:C16=J7)*1} -> 0 | L14: {=$E$5:$E$16*$D$5:$D$16} -> 2806 | M14: {=(C5:C16=J7)*1*E5:E16*D5:D16} -> 0
B15: Company2 | C15: HDD9 | D15: 115 | E15: 52 | F15: =D15*E15 -> 5980 | J15: FALSE | K15: 0 | L15: 1725 | M15: 0
B16: Company1 | C16: Clavier3 | D16: 77 | E16: 13 | F16: =D16*E16 -> 1001 | J16: FALSE | K16: 0 | L16: 5060 | M16: 0
E17: TOTAL 1 | F17: =SUM(F5:F16) -> 61443 | G17: =_xlfn.FORMULATEXT(F17) -> =SOMME(F5:F16) | J17: FALSE | K17: 0 | L17: 6475 | M17: 0
E18: TOTAL 2 | F18: =SUMPRODUCT(D5:D16,E5:E16) -> 61443 | G18: =_xlfn.FORMULATEXT(F18) -> =SOMMEPROD(D5:D16;E5:E16) | J18: FALSE | K18: 0 | L18: 4810 | M18: 0
J19: FALSE | K19: 0 | L19: 3145 | M19: 0
J20: FALSE | K20: 0 | L20: 3690 | M20: 0
J21: FALSE | K21: 0 | L21: 11615 | M21: 0
J22: TRUE | K22: 1 | L22: 7546 | M22: 7546
J23: FALSE | K23: 0 | L23: 7590 | M23: 0
J24: FALSE | K24: 0 | L24: 5980 | M24: 0
J25: FALSE | K25: 0 | L25: 1001 | M25: 0

Sheet 50. FILTER
A1: #VALUE! | B1: #VALUE! | C1: {=Translatefct(10,0)} -> FILTER | G1: {=Translatefct(10,1)} -> Returns an array of values that meet specified conditions.
B3: Department | C3: Employee | D3: Salary | E3: Born in | F3: Gender | G3: City | H3: Status | J3: Input | K3: finance | T3: {=TranslateMe(222)} -> logical test within a formula
B4: Finance | C4: Camille Dubois | D4: 5000 | E4: 1996 | F4: F | G4: Zurich | H4: Training | J4: {=TranslateMe(217)} -> FILTER WITH 1 CONDITION | T4: * | U4: AND
B5: Marketing | C5: Lucas Martin | D5: 5200 | E5: 2001 | F5: M | G5: Geneva | H5: Training | J5: =_xlfn.FORMULATEXT(K6) -> =FILTRE(rng_Filter;Department=$K$3;NotFound) | T5: + | U5: OR
B6: Sales | C6: Manon Lambert | D6: 8500 | E6: 1998 | F6: F | G6: Berne | H6: Active | K6: {=_xlfn._xlws.FILTER(rng_Filter,Department=$K$3,NotFound)} -> Finance | L6: Camille Dubois | M6: 5000 | N6: 1996 | O6: F | P6: Zurich | Q6: Training
B7: Sales | C7: Hugo Dupont | D7: 9800 | E7: 1965 | F7: M | G7: Geneva | H7: Active | K7: Finance | L7: Emma Garcia | M7: 7300 | N7: 1987 | O7: F | P7: Geneva | Q7: Active | T7: {=TranslateMe(223)} -> Don't forget the ( and ) around boolean comparisons !
B8: Finance | C8: Emma Garcia | D8: 7300 | E8: 1987 | F8: F | G8: Geneva | H8: Active | K8: Finance | L8: Léa Rousseau | M8: 4900 | N8: 1996 | O8: ND | P8: Geneva | Q8: Active
B9: Sales | C9: Louis Chevalier | D9: 10600 | E9: 1979 | F9: M | G9: Berne | H9: Active | K9: Finance | L9: Nathan Leroy | M9: 11750 | N9: 2005 | O9: F | P9: Zurich | Q9: Active
B10: Finance | C10: Léa Rousseau | D10: 4900 | E10: 1996 | F10: ND | G10: Geneva | H10: Active | K10: Finance | L10: Jade Simon | M10: 8900 | N10: 1961 | O10: F | P10: Geneva | Q10: Retired
B11: Finance | C11: Nathan Leroy | D11: 11750 | E11: 2005 | F11: F | G11: Zurich | H11: Active | K11: Finance | L11: Maxime Robin | M11: 13450 | N11: 1974 | O11: M | P11: Lausanne | Q11: Active
B12: Sales | C12: Chloé Lefebvre | D12: 9100 | E12: 2003 | F12: F | G12: Zurich | H12: Maternity leave | K12: Finance | L12: Sarah Thomas | M12: 13600 | N12: 1989 | O12: F | P12: Lausanne | Q12: Active
B13: Marketing | C13: Enzo Moreau | D13: 12300 | E13: 2001 | F13: M | G13: Geneva | H13: Active | K13: Finance | L13: Ethan Gauthier | M13: 7500 | N13: 2000 | O13: M | P13: Zurich | Q13: Active
B14: Sales | C14: Clara Mercier | D14: 7800 | E14: 1995 | F14: F | G14: Geneva | H14: Active
B15: Marketing | C15: Théo Laurent | D15: 10200 | E15: 1990 | F15: M | G15: Berne | H15: Active
B16: Sales | C16: Zoé Girard | D16: 6500 | E16: 1984 | F16: F | G16: Geneva | H16: Active
B17: Sales | C17: Gabriel Petit | D17: 11000 | E17: 1966 | F17: M | G17: Geneva | H17: Pre-retirement
B18: Finance | C18: Jade Simon | D18: 8900 | E18: 1961 | F18: F | G18: Geneva | H18: Retired
B19: Finance | C19: Maxime Robin | D19: 13450 | E19: 1974 | F19: M | G19: Lausanne | H19: Active
B20: Finance | C20: Sarah Thomas | D20: 13600 | E20: 1989 | F20: F | G20: Lausanne | H20: Active
B21: Marketing | C21: Mathis Leroux | D21: 6800 | E21: 1984 | F21: M | G21: Lausanne | H21: Sick Leave
B22: Marketing | C22: Inès Martinez | D22: 10300 | E22: 1998 | F22: F | G22: Geneva | H22: Active
B23: Finance | C23: Ethan Gauthier | D23: 7500 | E23: 2000 | F23: M | G23: Zurich | H23: Active
J25: {=TranslateMe(218)} -> FILTER WITH 2 CONDITIONS
J26: =_xlfn.FORMULATEXT(K27) -> =FILTRE($B$4:$D$23;(Department=$K$3)*(Salary>10000);NotFound)
K27: {=_xlfn._xlws.FILTER($B$4:$D$23,(Department=$K$3)*(Salary>10000),NotFound)} -> Finance | L27: Nathan Leroy | M27: 11750
K28: Finance | L28: Maxime Robin | M28: 13450
K29: Finance | L29: Sarah Thomas | M29: 13600
B33: {=TranslateMe(219)} -> FILTER AND CHOOSE COLUMNS | H33: {=TranslateMe(220)} -> FILTER FROM ARRAY FORMULA | N33: {=TranslateMe(221)} -> NESTED FILTERING
B34: =_xlfn.FORMULATEXT(C35) -> =FILTRE(rng_Filter;{0.1.0.1.1.0.1};NotFound) | H34: =_xlfn.FORMULATEXT(I35) -> =FILTRE($K$6#;{0.1.0.1.1.0.1};NotFound) | N34: =_xlfn.FORMULATEXT(O35) -> =FILTRE(FILTRE(rng_Filter;Department=$K$3;NotFound);{0.1.0.1.1.0.1};NotFound)
C35: {=_xlfn._xlws.FILTER(rng_Filter,{0,1,0,1,1,0,1},NotFound)} -> Camille Dubois | D35: 1996 | E35: F | F35: Training | I35: {=_xlfn._xlws.FILTER(_xlfn.ANCHORARRAY($K$6),{0,1,0,1,1,0,1},NotFound)} -> Camille Dubois | J35: 1996 | K35: F | L35: Training | O35: {=_xlfn._xlws.FILTER(_xlfn._xlws.FILTER(rng_Filter,Department=$K$3,NotFound),{0,1,0,1,1,0,1},NotFound)} -> Camille Dubois | P35: 1996 | Q35: F | R35: Training
C36: Lucas Martin | D36: 2001 | E36: M | F36: Training | I36: Emma Garcia | J36: 1987 | K36: F | L36: Active | O36: Emma Garcia | P36: 1987 | Q36: F | R36: Active
C37: Manon Lambert | D37: 1998 | E37: F | F37: Active | I37: Léa Rousseau | J37: 1996 | K37: ND | L37: Active | O37: Léa Rousseau | P37: 1996 | Q37: ND | R37: Active
C38: Hugo Dupont | D38: 1965 | E38: M | F38: Active | I38: Nathan Leroy | J38: 2005 | K38: F | L38: Active | O38: Nathan Leroy | P38: 2005 | Q38: F | R38: Active
C39: Emma Garcia | D39: 1987 | E39: F | F39: Active | I39: Jade Simon | J39: 1961 | K39: F | L39: Retired | O39: Jade Simon | P39: 1961 | Q39: F | R39: Retired
C40: Louis Chevalier | D40: 1979 | E40: M | F40: Active | I40: Maxime Robin | J40: 1974 | K40: M | L40: Active | O40: Maxime Robin | P40: 1974 | Q40: M | R40: Active
C41: Léa Rousseau | D41: 1996 | E41: ND | F41: Active | I41: Sarah Thomas | J41: 1989 | K41: F | L41: Active | O41: Sarah Thomas | P41: 1989 | Q41: F | R41: Active
C42: Nathan Leroy | D42: 2005 | E42: F | F42: Active | I42: Ethan Gauthier | J42: 2000 | K42: M | L42: Active | O42: Ethan Gauthier | P42: 2000 | Q42: M | R42: Active
C43: Chloé Lefebvre | D43: 2003 | E43: F | F43: Maternity leave
C44: Enzo Moreau | D44: 2001 | E44: M | F44: Active
C45: Clara Mercier | D45: 1995 | E45: F | F45: Active
C46: Théo Laurent | D46: 1990 | E46: M | F46: Active
C47: Zoé Girard | D47: 1984 | E47: F | F47: Active
C48: Gabriel Petit | D48: 1966 | E48: M | F48: Pre-retirement
C49: Jade Simon | D49: 1961 | E49: F | F49: Retired
C50: Maxime Robin | D50: 1974 | E50: M | F50: Active
C51: Sarah Thomas | D51: 1989 | E51: F | F51: Active
C52: Mathis Leroux | D52: 1984 | E52: M | F52: Sick Leave
C53: Inès Martinez | D53: 1998 | E53: F | F53: Active
C54: Ethan Gauthier | D54: 2000 | E54: M | F54: Active
C56: {=Translatefct(10,0)} -> FILTER | F56: {=TranslateMe(244)} -> within a table
B57: Department | C57: Employee | D57: Salary | E57: Born in | F57: Gender | G57: City | H57: Status | J57: {=TranslateMe(217)} -> FILTER WITH 1 CONDITION
B58: Finance | C58: Camille Dubois | D58: 5000 | E58: 1996 | F58: F | G58: Zurich | H58: Training | J58: =_xlfn.FORMULATEXT(J59) -> =FILTRE(tbl_filtre;tbl_filtre[Department]="Sales";NotFound)
B59: Marketing | C59: Lucas Martin | D59: 5200 | E59: 2001 | F59: M | G59: Geneva | H59: Training | J59: {=_xlfn._xlws.FILTER(tbl_filtre[],tbl_filtre[Department]="Sales",NotFound)} -> Sales | K59: Manon Lambert | L59: 8500 | M59: 1998 | N59: F | O59: Berne | P59: Active
B60: Sales | C60: Manon Lambert | D60: 8500 | E60: 1998 | F60: F | G60: Berne | H60: Active | J60: Sales | K60: Hugo Dupont | L60: 9800 | M60: 1965 | N60: M | O60: Geneva | P60: Active
B61: Sales | C61: Hugo Dupont | D61: 9800 | E61: 1965 | F61: M | G61: Geneva | H61: Active | J61: Sales | K61: Louis Chevalier | L61: 10600 | M61: 1979 | N61: M | O61: Berne | P61: Active
B62: Finance | C62: Emma Garcia | D62: 7300 | E62: 1987 | F62: F | G62: Geneva | H62: Active | J62: Sales | K62: Chloé Lefebvre | L62: 9100 | M62: 2003 | N62: F | O62: Zurich | P62: Maternity leave
B63: Sales | C63: Louis Chevalier | D63: 10600 | E63: 1979 | F63: M | G63: Berne | H63: Active | J63: Sales | K63: Clara Mercier | L63: 7800 | M63: 1995 | N63: F | O63: Geneva | P63: Active
B64: Finance | C64: Léa Rousseau | D64: 4900 | E64: 1996 | F64: ND | G64: Geneva | H64: Active | J64: Sales | K64: Zoé Girard | L64: 6500 | M64: 1984 | N64: F | O64: Geneva | P64: Active
B65: Finance | C65: Nathan Leroy | D65: 11750 | E65: 2005 | F65: F | G65: Zurich | H65: Active | J65: Sales | K65: Gabriel Petit | L65: 11000 | M65: 1966 | N65: M | O65: Geneva | P65: Pre-retirement
B66: Sales | C66: Chloé Lefebvre | D66: 9100 | E66: 2003 | F66: F | G66: Zurich | H66: Maternity leave
B67: Marketing | C67: Enzo Moreau | D67: 12300 | E67: 2001 | F67: M | G67: Geneva | H67: Active
B68: Sales | C68: Clara Mercier | D68: 7800 | E68: 1995 | F68: F | G68: Geneva | H68: Active
B69: Marketing | C69: Théo Laurent | D69: 10200 | E69: 1990 | F69: M | G69: Berne | H69: Active | J69: {=TranslateMe(242)} -> FILTER WITH WILDCARD
B70: Sales | C70: Zoé Girard | D70: 6500 | E70: 1984 | F70: F | G70: Geneva | H70: Active | J70: {=TranslateMe(243)} -> Value to look for (in name) | L70: ma
B71: Sales | C71: Gabriel Petit | D71: 11000 | E71: 1966 | F71: M | G71: Geneva | H71: Pre-retirement | J71: =_xlfn.FORMULATEXT(J72) -> =ESTNUM(CHERCHE($L$70;tbl_filtre[Employee]))
B72: Finance | C72: Jade Simon | D72: 8900 | E72: 1961 | F72: F | G72: Geneva | H72: Retired | J72: {=ISNUMBER(SEARCH($L$70,tbl_filtre[Employee]))} -> FALSE
B73: Finance | C73: Maxime Robin | D73: 13450 | E73: 1974 | F73: M | G73: Lausanne | H73: Active | J73: TRUE | L73: =_xlfn.FORMULATEXT(L74) -> =FILTRE(tbl_filtre;J72#;NotFound)
B74: Finance | C74: Sarah Thomas | D74: 13600 | E74: 1989 | F74: F | G74: Lausanne | H74: Active | J74: TRUE | L74: {=_xlfn._xlws.FILTER(tbl_filtre[],_xlfn.ANCHORARRAY(J72),NotFound)} -> Marketing | M74: Lucas Martin | N74: 5200 | O74: 2001 | P74: M | Q74: Geneva | R74: Training
B75: Marketing | C75: Mathis Leroux | D75: 6800 | E75: 1984 | F75: M | G75: Lausanne | H75: Sick Leave | J75: FALSE | L75: Sales | M75: Manon Lambert | N75: 8500 | O75: 1998 | P75: F | Q75: Berne | R75: Active
B76: Marketing | C76: Inès Martinez | D76: 10300 | E76: 1998 | F76: F | G76: Geneva | H76: Active | J76: TRUE | L76: Finance | M76: Emma Garcia | N76: 7300 | O76: 1987 | P76: F | Q76: Geneva | R76: Active
B77: Finance | C77: Emma Gauthier | D77: 7500 | E77: 2000 | F77: M | G77: Zurich | H77: Active | J77: FALSE | L77: Finance | M77: Maxime Robin | N77: 13450 | O77: 1974 | P77: M | Q77: Lausanne | R77: Active
J78: FALSE | L78: Finance | M78: Sarah Thomas | N78: 13600 | O78: 1989 | P78: F | Q78: Lausanne | R78: Active
J79: FALSE | L79: Marketing | M79: Mathis Leroux | N79: 6800 | O79: 1984 | P79: M | Q79: Lausanne | R79: Sick Leave
J80: FALSE | L80: Marketing | M80: Inès Martinez | N80: 10300 | O80: 1998 | P80: F | Q80: Geneva | R80: Active
J81: FALSE | L81: Finance | M81: Emma Gauthier | N81: 7500 | O81: 2000 | P81: M | Q81: Zurich | R81: Active
J82: FALSE
J83: FALSE
J84: FALSE
J85: FALSE
B86: {=TranslateMe(245)} -> FILTER AND CHOOSE COLUMNS | J86: FALSE
B87: =_xlfn.FORMULATEXT(B88) -> =FILTRE(CHOISIRCOLS(tbl_filtre;1;2;4;5);tbl_filtre[City]="Geneva";NotFound) | J87: TRUE
B88: {=_xlfn._xlws.FILTER(_xlfn.CHOOSECOLS(tbl_filtre[],1,2,4,5),tbl_filtre[City]="Geneva",NotFound)} -> Marketing | C88: Lucas Martin | D88: 2001 | E88: M | J88: TRUE
B89: Sales | C89: Hugo Dupont | D89: 1965 | E89: M | J89: TRUE
B90: Finance | C90: Emma Garcia | D90: 1987 | E90: F | J90: TRUE
B91: Finance | C91: Léa Rousseau | D91: 1996 | E91: ND | J91: TRUE
B92: Marketing | C92: Enzo Moreau | D92: 2001 | E92: M
B93: Sales | C93: Clara Mercier | D93: 1995 | E93: F
B94: Sales | C94: Zoé Girard | D94: 1984 | E94: F
B95: Sales | C95: Gabriel Petit | D95: 1966 | E95: M
B96: Finance | C96: Jade Simon | D96: 1961 | E96: F
B97: Marketing | C97: Inès Martinez | D97: 1998 | E97: F

Sheet 50. SORT
A1: #VALUE! | B1: #VALUE! | E1: {=Translatefct(20,0)} -> SORT | J1: {=Translatefct(30,0)} -> SORTBY
E2: {=Translatefct(20,1)} -> Sorts the contents of an array or range. | J2: {=Translatefct(30,1)} -> Sorts an array based on the values in a corresponding array.
B3: {=txt_dpt} -> Department | C3: {=txt_Employe} -> Employee | D3: {=txt_salaire} -> Salary | F3: {=TranslateMe(225)} -> Sort a Table on salary ASC | J3: {=TranslateMe(226)} -> Multi-column sort
B4: Finance | C4: Camille Dubois | D4: 5000 | F4: =_xlfn.FORMULATEXT(F5) -> =TRIER(B4:D23;3;1) | J4: =_xlfn.FORMULATEXT(J5) -> =TRIERPAR(F5#;F5:F24;1;G5:G24;1)
B5: Marketing | C5: Lucas Martin | D5: 6200 | F5: {=_xlfn._xlws.SORT(B4:D23,3,1)} -> Finance | G5: Léa Rousseau | H5: 4900 | J5: {=_xlfn.SORTBY(_xlfn.ANCHORARRAY(F5),F5:F24,1,G5:G24,1)} -> Finance | K5: Camille Dubois | L5: 5000 | O5: {=_xlfn.SORTBY(_xlfn.ANCHORARRAY(F5),F5:F24,1,H5:H24,-1)} -> Finance | P5: Ethan Gauthier | Q5: 17500
B6: Ventes | C6: Manon Lambert | D6: 8500 | F6: Finance | G6: Camille Dubois | H6: 5000 | J6: Finance | K6: Emma Garcia | L6: 7300 | O6: Finance | P6: Maxime Robin | Q6: 13450
B7: Ventes | C7: Hugo Dupont | D7: 9800 | F7: Marketing | G7: Lucas Martin | H7: 6200 | J7: Finance | K7: Ethan Gauthier | L7: 17500 | O7: Finance | P7: Nathan Leroy | Q7: 11750
B8: Finance | C8: Emma Garcia | D8: 7300 | F8: Ventes | G8: Zoé Girard | H8: 6500 | J8: Finance | K8: Jade Simon | L8: 8900 | O8: Finance | P8: Sarah Thomas | Q8: 11600
B9: Ventes | C9: Louis Chevalier | D9: 10600 | F9: Finance | G9: Emma Garcia | H9: 7300 | J9: Finance | K9: Léa Rousseau | L9: 4900 | O9: Finance | P9: Jade Simon | Q9: 8900
B10: Finance | C10: Léa Rousseau | D10: 4900 | F10: Ventes | G10: Clara Mercier | H10: 7800 | J10: Finance | K10: Maxime Robin | L10: 13450 | O10: Finance | P10: Emma Garcia | Q10: 7300
B11: Finance | C11: Nathan Leroy | D11: 11750 | F11: Ventes | G11: Manon Lambert | H11: 8500 | J11: Finance | K11: Nathan Leroy | L11: 11750 | O11: Finance | P11: Camille Dubois | Q11: 5000
B12: Ventes | C12: Chloé Lefebvre | D12: 9100 | F12: Finance | G12: Jade Simon | H12: 8900 | J12: Finance | K12: Sarah Thomas | L12: 11600 | O12: Finance | P12: Léa Rousseau | Q12: 4900
B13: Marketing | C13: Enzo Moreau | D13: 12300 | F13: Ventes | G13: Chloé Lefebvre | H13: 9100 | J13: Marketing | K13: Enzo Moreau | L13: 12300 | O13: Marketing | P13: Mathis Leroux | Q13: 16800
B14: Ventes | C14: Clara Mercier | D14: 7800 | F14: Ventes | G14: Hugo Dupont | H14: 9800 | J14: Marketing | K14: Inès Martinez | L14: 10300 | O14: Marketing | P14: Théo Laurent | Q14: 15200
B15: Marketing | C15: Théo Laurent | D15: 15200 | F15: Marketing | G15: Inès Martinez | H15: 10300 | J15: Marketing | K15: Lucas Martin | L15: 6200 | O15: Marketing | P15: Enzo Moreau | Q15: 12300
B16: Ventes | C16: Zoé Girard | D16: 6500 | F16: Ventes | G16: Louis Chevalier | H16: 10600 | J16: Marketing | K16: Mathis Leroux | L16: 16800 | O16: Marketing | P16: Inès Martinez | Q16: 10300
B17: Ventes | C17: Gabriel Petit | D17: 14000 | F17: Finance | G17: Sarah Thomas | H17: 11600 | J17: Marketing | K17: Théo Laurent | L17: 15200 | O17: Marketing | P17: Lucas Martin | Q17: 6200
... B23: Finance | C23: Ethan Gauthier | D23: 17500 | F23: Marketing | G23: Mathis Leroux | H23: 16800 | J23: Ventes | K23: Manon Lambert | L23: 8500 | O23: Ventes | P23: Clara Mercier | Q23: 7800
F24: Finance | G24: Ethan Gauthier | H24: 17500 | J24: Ventes | K24: Zoé Girard | L24: 6500 | O24: Ventes | P24: Zoé Girard | Q24: 6500
I25: =LEFT(G25,1)
F26: {=TranslateMe(227)} -> Sorting the salary column DESC
F27: =_xlfn.FORMULATEXT(F28) -> =TRIER(B4:D23;3;-1) | J27: =_xlfn.FORMULATEXT(J28) -> =UNIQUE(B4:B22) | L27: =_xlfn.FORMULATEXT(L28) -> =TRIER(J28#)
F28: {=_xlfn._xlws.SORT(B4:D23,3,-1)} -> Finance | G28: Ethan Gauthier | H28: 17500 | J28: {=_xlfn.UNIQUE(B4:B22)} -> Finance | L28: {=_xlfn._xlws.SORT(_xlfn.ANCHORARRAY(J28))} -> Finance
F29: Marketing | G29: Mathis Leroux | H29: 16800 | J29: Marketing | L29: Marketing
F30: Marketing | G30: Théo Laurent | H30: 15200 | J30: Ventes | L30: Ventes
F31: Ventes | G31: Gabriel Petit | H31: 14000
F32: Finance | G32: Maxime Robin | H32: 13450
F33: Marketing | G33: Enzo Moreau | H33: 12300
F34: Finance | G34: Nathan Leroy | H34: 11750
F35: Finance | G35: Sarah Thomas | H35: 11600
F36: Ventes | G36: Louis Chevalier | H36: 10600
F37: Marketing | G37: Inès Martinez | H37: 10300
F38: Ventes | G38: Hugo Dupont | H38: 9800
F39: Ventes | G39: Chloé Lefebvre | H39: 9100
F40: Finance | G40: Jade Simon | H40: 8900
F41: Ventes | G41: Manon Lambert | H41: 8500
F42: Ventes | G42: Clara Mercier | H42: 7800
... F47: Finance | G47: Léa Rousseau | H47: 4900

Sheet 60. INDEX
A1: #VALUE! | C1: {=TranslateMe(25)} -> INDEX | XMATCH | OFFSET
B2: ID | C2: Cat | D2: Nom | F2: {=TranslateMe(230)} -> COL | G2: 17
B3: 1 | C3: Sports | D3: Didier Cuche | F3: {=TranslateMe(229)} -> ROW | G3: 3
B4: 2 | C4: Politique | D4: Pascal Couchepin | F4: {=Translatefct(830,0)} -> INDEX | G4: {=Translatefct(830,1)} -> Returns the value of a cell at the intersection of a row and column in a range.
B5: 3 | C5: Business/Innovation | D5: Hansjörg Wyss | F5: {=TranslateMe(231)} -> Who's in row 17 and col 3 ?
B6: 4 | C6: Science | D6: Bertrand Piccard | F6: {=INDEX($B$3:$D$33,$G$2,$G$3)} -> Nicolas Hayek | H6: =_xlfn.FORMULATEXT(F6) -> =INDEX($B$3:$D$33;$G$2;$G$3)
B7: 5 | C7: Politique | D7: Ueli Maurer
B8: 6 | C8: Business/Innovation | D8: Henri Nestlé
B9: 7 | C9: Histoire | D9: Carl Jung | F9: {=Translatefct(180,0)} -> XMATCH | G9: {=Translatefct(180,1)} -> Finds the relative position of a value in an array (replacement for MATCH).
B10: 8 | C10: Histoire | D10: Jean-Jacques Rousseau | F10: {=TranslateMe(232)} -> Which column contains this data ? | H10: Cat
B11: 9 | C11: Politique | D11: Ignazio Cassis | F11: =_xlfn.XMATCH(H10,$B$2:$D$2,0) -> 2 | H11: =_xlfn.FORMULATEXT(F11) -> =EQUIVX(H10;$B$2:$D$2;0)
B12: 10 | C12: Business/Innovation | D12: Ernesto Bertarelli
B13: 11 | C13: Politique | D13: Jean-Pascal Delamuraz | F13: {=TranslateMe(233)} -> Show the row number of | G13: Paul Klee
B14: 12 | C14: Sports | D14: Roger Federer | F14: =_xlfn.XMATCH($G$13,$D$3:$D$33,0) -> 16 | H14: =_xlfn.FORMULATEXT(F14) -> =EQUIVX($G$13;$D$3:$D$33;0)
B15: 13 | C15: Histoire | D15: Henry Dunant
B16: 14 | C16: Auteur / Artiste | D16: Johanna Spyri | F16: {=Translatefct(840,0)} -> OFFSET | G16: {=Translatefct(840,1)} -> Returns a reference to a range that is offset from a starting cell by rows and columns.
B17: 15 | C17: Politique | D17: Guy Parmelin | F17: {=TranslateMe(234)} -> Which category is Paul Klee in ?
B18: 16 | C18: Auteur / Artiste | D18: Paul Klee | F18: =OFFSET($B$2,$F$14,$F$11-1) -> Auteur / Artiste | H18: =_xlfn.FORMULATEXT(F18) -> =DECALER($B$2;$F$14;$F$11-1)
B19: 17 | C19: Business/Innovation | D19: Nicolas Hayek
B20: 18 | C20: Histoire | D20: William Tell | F20: {=Translatefct(840,0)} -> OFFSET | G20: {=Translatefct(840,1)} -> Returns a reference to a range that is offset from a starting cell by rows and columns.
B21: 19 | C21: Histoire | D21: Alberto Giacometti | F21: {=OFFSET(B2,F14,1,3,2)} -> Auteur / Artiste | G21: Paul Klee | H21: =_xlfn.FORMULATEXT(F21) -> =DECALER(B2;F14;1;3;2)
B22: 20 | C22: Sports | D22: Martina Hingis | F22: Business/Innovation | G22: Nicolas Hayek
B23: 21 | C23: Business/Innovation | D23: Daniel Borel | F23: Histoire | G23: William Tell
B24: 22 | C24: Politique | D24: Simonetta Sommaruga
B25: 23 | C25: Histoire | D25: Auguste Piccard | F25: {=Translatefct(840,0)} -> OFFSET | G25: {=Translatefct(840,1)} -> Returns a reference to a range that is offset from a starting cell by rows and columns.
B26: 24 | C26: Histoire | D26: Leonhard Euler | F26: {=OFFSET(D33,-1,-1,-2,-2)} -> 29 | G26: Auteur / Artiste | H26: =_xlfn.FORMULATEXT(F26) -> =DECALER(D33;-1;-1;-2;-2)
B27: 25 | C27: Sports | D27: Lara Gut-Behrami | F27: 30 | G27: Auteur / Artiste
B28: 26 | C28: Politique | D28: Micheline Calmy-Rey
B29: 27 | C29: Science | D29: Albert Einstein
B30: 28 | C30: Sports | D30: Stan Wawrinka | F30: {=TranslateMe(235)} -> FIND ALL PEOPLE IN THE SAME CATEGORY AS PAUL KLEE
B31: 29 | C31: Auteur / Artiste | D31: Hermann Hesse | F31: {=_xlfn._xlws.FILTER($B$2:$D$32,$C$2:$C$32=OFFSET(B2,F14,1))} -> 14 | G31: Auteur / Artiste | H31: Johanna Spyri
B32: 30 | C32: Auteur / Artiste | D32: Friedrich Dürrenmatt | F32: 16 | G32: Auteur / Artiste | H32: Paul Klee
F33: 29 | G33: Auteur / Artiste | H33: Hermann Hesse
F34: 30 | G34: Auteur / Artiste | H34: Friedrich Dürrenmatt

Sheet 60. VLOOKUP
A1: #VALUE! | C1: {=Translatefct(850,0)} -> VLOOKUP | I1: {=Translatefct(850,1)} -> Searches for a value in the first column of a range and returns a value in the same row. VLOOKUP( VALUE; SEARCH RANGE; RETURN COLUMN NUMBER; 0/1 )
B2: Name | C2: ID | D2: Department | E2: Region | F2: Gender | G2: Born in | H2: Solde vacances
B3: James Willard | C3: ID18 | D3: Sales | E3: Bern | F3: M | G3: 1968 | H3: 68 | J3: {=TranslateMe(237)} -> VLOOKUP WITH WILDCARD
B4: Robert Spear | C4: ID8 | D4: Sales | E4: Bern | F4: M | G4: 1988 | H4: 986 | K4: Dan
B5: Paul Garza | C5: ID24 | D5: Sales | E5: Bern | F5: M | G5: 1990 | H5: 175 | K5: =VLOOKUP($K$4&"*",$B$3:$E$40,2,0) -> ID28 | L5: =_xlfn.FORMULATEXT(K5) -> =RECHERCHEV($K$4&"*";$B$3:$E$40;2;0)
B6: Robert Marquez | C6: ID23 | D6: Sales | E6: Bern | F6: M | G6: 1985 | H6: 339
B7: Kim Montreux | C7: ID13 | D7: Sales | E7: Bern | F7: M | G7: 2003 | H7: 433 | K7: Natalie Porter
B8: Stevie Bridge | C8: ID7 | D8: Sales | E8: Bern | F8: M | G8: 2005 | H8: -22 | K8: Region
B9: Paul Wells | C9: ID19 | D9: Sales | E9: Bern | F9: M | G9: 1996 | H9: 116
B10: Ewan Thompson | C10: ID22 | D10: Sales | E10: Geneva | F10: M | G10: 1984 | H10: 749
B11: Walter Miller | C11: ID5 | D11: Sales | E11: Geneva | F11: M | G11: 1974 | H11: 343 | J11: {=TranslateMe(238)} -> SEARCH WITH INDEX AND MATCH
B12: Peter Ramsy | C12: ID9 | D12: Sales | E12: Geneva | F12: M | G12: 1977 | H12: 51 | J12: =INDEX(B2:E40,MATCH($K$7,$B$2:$B$40,0),MATCH($K$8,$B$2:$E$2,0)) -> Biel | L12: =_xlfn.FORMULATEXT(J12) -> =INDEX(B2:E40;EQUIV($K$7;$B$2:$B$40;0);EQUIV($K$8;$B$2:$E$2;0))
B13: Wolfgang Ramjac | C13: ID17 | D13: Sales | E13: Geneva | F13: M | G13: 1999 | H13: 795
B14: Brigitte Bond | C14: ID10 | D14: Sales | E14: Geneva | F14: F | G14: 1968 | H14: 519
B15: Maria Tot | C15: ID21 | D15: Sales | E15: Geneva | F15: F | G15: 1988 | H15: 117 | J15: {=TranslateMe(239)} -> HORIZONTAL MATRIX VLOOKUP
B16: Natalie Porter | C16: ID3 | D16: Procurement | E16: Biel | F16: F | G16: 1990 | H16: 223 | J16: {=VLOOKUP($K$7,B3:G40,{4,2,6,5},FALSE)} -> Biel | K16: ID3 | L16: 1990 | M16: F | N16: =_xlfn.FORMULATEXT(J16) -> =RECHERCHEV($K$7;B3:G40;{4.2.6.5};FAUX)
B17: Andre Cooper | C17: ID29 | D17: Procurement | E17: Biel | F17: M | G17: 1985 | H17: 958
B18: Robert Musser | C18: ID30 | D18: Procurement | E18: Biel | F18: M | G18: 2003 | H18: 832 | J18: {=TranslateMe(240)} -> VERTICAL MATRIX VLOOKUP
B19: Ann Withers | C19: ID14 | D19: Procurement | E19: Biel | F19: F | G19: 2005 | H19: 302 | J19: {=VLOOKUP($K$7,B3:H40,_xlfn.SEQUENCE(4,1,3,1),FALSE)} -> Procurement
B20: Corinna Schmidt | C20: ID16 | D20: Procurement | E20: Biel | F20: F | G20: 1996 | H20: 967 | J20: Biel | K20: =_xlfn.FORMULATEXT(J19) -> =RECHERCHEV($K$7;B3:H40;SEQUENCE(4;1;3;1);FAUX)
B21: Mike Saban | C21: ID27 | D21: Procurement | E21: Biel | F21: M | G21: 1984 | H21: 629 | J21: F
B22: Gary Miller | C22: ID4 | D22: Finance | E22: Zurich | F22: M | G22: 1974 | H22: 827 | J22: 1990
B23: Richard Elliot | C23: ID12 | D23: Finance | E23: Zurich | F23: M | G23: 1977 | H23: 454
B24: Roger Mun | C24: ID20 | D24: Finance | E24: Zurich | F24: M | G24: 1999 | H24: 835
B25: Daniel Garrett | C25: ID28 | D25: Finance | E25: Zurich | F25: M | G25: 1968 | H25: 344
B26: Paul Hill | C26: ID25 | D26: Finance | E26: Zurich | F26: M | G26: 1988 | H26: 3
B27: Crystal Doyle | C27: ID1 | D27: Finance | E27: Zurich | F27: ND | G27: 1990 | H27: -28
B28: Betina Bauer | C28: ID15 | D28: Finance | E28: Lausanne | F28: F | G28: 1985 | H28: 230
B29: Daniela Schreiber | C29: ID2 | D29: Finance | E29: Lausanne | F29: F | G29: 2003 | H29: 941
B30: Dan Ziegler | C30: ID11 | D30: Finance | E30: Lausanne | F30: M | G30: 2005 | H30: 503
B31: Robert Richardson | C31: ID26 | D31: Finance | E31: Lausanne | F31: M | G31: 1996 | H31: 2
B32: Robert Blume | C32: ID6 | D32: Finance | E32: Lausanne | F32: M | G32: 1984 | H32: 302
B33: Lukas Hofer | C33: ID31 | D33: Finance | E33: Lausanne | F33: M | G33: 1974 | H33: 254
B34: Corina Doyle | C34: ID1 | D34: Finance | E34: Zurich | F34: F | G34: 1977 | H34: 310
... B40: Lukas Hofer | C40: ID31 | D40: Finance | E40: Lausanne | F40: M | G40: 2007 | H40: 930

Sheet 60. XLOOKUP
A1: #VALUE! | B1: #VALUE! | C1: {=Translatefct(170,0)} -> XLOOKUP | E1: {=Translatefct(170,1)} -> Advanced replacement for VLOOKUP and HLOOKUP, allowing for flexible lookups. XLOOKUP(lookup_value, lookup_array, return_array, [if_not_found], [match_mode], [search_mode]) | L1: 0 Exact match (default). If no exact match is found, returns #N/A. -1 Exact match or next smaller item. 1 Exact match or next larger item. 2 Wildcard match. Supports *, ?, and ~ in the lookup value. | N1: 1 Search from first to last (top to bottom or left to right) — default -1 Search from last to first (bottom to top or right to left)
D2: =_xlfn.FORMULATEXT(E23) -> =RECHERCHEX([@[Nom / Name]];Tableau_bonus[Nom];Tableau_bonus[Bonus %];0)*D23 | L2: {=IF(eng_flag,"match_mode","mode_correspondance")} -> match_mode | N2: {=IF(eng_flag,"search_mode","mode_recherche")} -> search_mode
F3: =_xlfn.FORMULATEXT(G23) -> =RECHERCHEX(D23;$G$56:$G$60;$H$56:$H$60;;-1)*D23
B4: tbl_Presidents | J4: {=TranslateMe(82)} -> Basic XLOOKUP (to the left)
B5: Année / Year | C5: Nom / Name | D5: Base | E5: Bonus | F5: Base+Bonus | G5: Extra Bonus | H5: Total | J5: Flavio Cotti
B6: 1980 | C6: Georges-André Chevallaz | D6: 150000 | E6: =_xlfn.XLOOKUP(tbl_Presidents[[#This Row],[Nom / Name]],Tableau_bonus[Nom],Tableau_bonus[Bonus %],0)*D6 -> 33000 | F6: =D6+E6 -> 183000 | G6: =_xlfn.XLOOKUP(D6,$G$56:$G$60,$H$56:$H$60,,-1)*D6 -> 0 | H6: =SUM(F6:G6) -> 183000 | J6: =_xlfn.XLOOKUP($J$5,tbl_Presidents[Nom / Name],tbl_Presidents[Année / Year]) -> 1991
B7: 1981 | C7: Kurt Furgler | D7: 150818 | E7: =_xlfn.XLOOKUP(tbl_Presidents[[#This Row],[Nom / Name]],Tableau_bonus[Nom],Tableau_bonus[Bonus %],0)*D7 -> 37704.5 | F7: =D7+E7 -> 188522.5 | G7: =_xlfn.XLOOKUP(D7,$G$56:$G$60,$H$56:$H$60,,-1)*D7 -> 0 | H7: =SUM(F7:G7) -> 188522.5
B8: 1982 | C8: Fritz Honegger | D8: 151624 | E8: =_xlfn.XLOOKUP(tbl_Presidents[[#This Row],[Nom / Name]],Tableau_bonus[Nom],Tableau_bonus[Bonus %],0)*D8 -> 37906 | F8: =D8+E8 -> 189530 | G8: =_xlfn.XLOOKUP(D8,$G$56:$G$60,$H$56:$H$60,,-1)*D8 -> 0 | H8: =SUM(F8:G8) -> 189530 | J8: {=TranslateMe(83)} -> XLOOKUP multiple values | M8: {=TranslateMe(84)} -> XLOOKUP multiple results
B9: 1983 | C9: Pierre Aubert | D9: 152499 | E9: =_xlfn.XLOOKUP(tbl_Presidents[[#This Row],[Nom / Name]],Tableau_bonus[Nom],Tableau_bonus[Bonus %],0)*D9 -> 38124.75 | F9: =D9+E9 -> 190623.75 | G9: =_xlfn.XLOOKUP(D9,$G$56:$G$60,$H$56:$H$60,,-1)*D9 -> 0 | H9: =SUM(F9:G9) -> 190623.75 | J9: Fritz Honegger | K9: {=_xlfn.XLOOKUP(J9:J11,tbl_Presidents[Nom / Name],tbl_Presidents[Année / Year])} -> 1982 | M9: Flavio Cotti
B10: 1984 | C10: Leon Schlumpf | D10: 152384 | E10: =_xlfn.XLOOKUP(tbl_Presidents[[#This Row],[Nom / Name]],Tableau_bonus[Nom],Tableau_bonus[Bonus %],0)*D10 -> 38096 | F10: =D10+E10 -> 190480 | G10: =_xlfn.XLOOKUP(D10,$G$56:$G$60,$H$56:$H$60,,-1)*D10 -> 0 | H10: =SUM(F10:G10) -> 190480 | J10: Jean-Pascal Delamuraz | K10: 1988 | M10: {=_xlfn.XLOOKUP($M$9,tbl_Presidents[Nom / Name],tbl_Presidents[[Base]:[Total]])} -> 159548 | N10: 30314.12 | O10: 189862.12 | P10: 0 | Q10: 189862.12
B11: 1985 | C11: Alphons Egli | D11: 154665 | E11: =_xlfn.XLOOKUP(tbl_Presidents[[#This Row],[Nom / Name]],Tableau_bonus[Nom],Tableau_bonus[Bonus %],0)*D11 -> 37119.6 | F11: =D11+E11 -> 191784.6 | G11: =_xlfn.XLOOKUP(D11,$G$56:$G$60,$H$56:$H$60,,-1)*D11 -> 0 | H11: =SUM(F11:G11) -> 191784.6 | J11: Elisabeth Kopp | K11: 1989
B12: 1986 | C12: Alphons Egli | D12: 155766 | E12: =_xlfn.XLOOKUP(tbl_Presidents[[#This Row],[Nom / Name]],Tableau_bonus[Nom],Tableau_bonus[Bonus %],0)*D12 -> 37383.84 | F12: =D12+E12 -> 193149.84 | G12: =_xlfn.XLOOKUP(D12,$G$56:$G$60,$H$56:$H$60,,-1)*D12 -> 0 | H12: =SUM(F12:G12) -> 193149.84
B13: 1987 | C13: Otto Stich | D13: 155124 | E13: =_xlfn.XLOOKUP(tbl_Presidents[[#This Row],[Nom / Name]],Tableau_bonus[Nom],Tableau_bonus[Bonus %],0)*D13 -> 35678.52 | F13: =D13+E13 -> 190802.52 | G13: =_xlfn.XLOOKUP(D13,$G$56:$G$60,$H$56:$H$60,,-1)*D13 -> 0 | H13: =SUM(F13:G13) -> 190802.52 | J13: {=TranslateMe(85)} -> XLOOKUP with wildcard
B14: 1988 | C14: Jean-Pascal Delamuraz | D14: 155072 | E14: =_xlfn.XLOOKUP(tbl_Presidents[[#This Row],[Nom / Name]],Tableau_bonus[Nom],Tableau_bonus[Bonus %],0)*D14 -> 35666.56 | F14: =D14+E14 -> 190738.56 | G14: =_xlfn.XLOOKUP(D14,$G$56:$G$60,$H$56:$H$60,,-1)*D14 -> 0 | H14: =SUM(F14:G14) -> 190738.56 | J14: *Ogi
B15: 1989 | C15: Elisabeth Kopp | D15: 156273 | E15: =_xlfn.XLOOKUP(tbl_Presidents[[#This Row],[Nom / Name]],Tableau_bonus[Nom],Tableau_bonus[Bonus %],0)*D15 -> 32817.33 | F15: =D15+E15 -> 189090.33 | G15: =_xlfn.XLOOKUP(D15,$G$56:$G$60,$H$56:$H$60,,-1)*D15 -> 0 | H15: =SUM(F15:G15) -> 189090.33 | J15: =_xlfn.XLOOKUP($J$14,tbl_Presidents[Nom / Name],tbl_Presidents[Année / Year],"not found",2) -> 1993
B16: 1990 | C16: Arnold Koller | D16: 156720 | E16: =_xlfn.XLOOKUP(tbl_Presidents[[#This Row],[Nom / Name]],Tableau_bonus[Nom],Tableau_bonus[Bonus %],0)*D16 -> 31344 | F16: =D16+E16 -> 188064 | G16: =_xlfn.XLOOKUP(D16,$G$56:$G$60,$H$56:$H$60,,-1)*D16 -> 0 | H16: =SUM(F16:G16) -> 188064
B17: 1991 | C17: Flavio Cotti | D17: 159548 | E17: =_xlfn.XLOOKUP(tbl_Presidents[[#This Row],[Nom / Name]],Tableau_bonus[Nom],Tableau_bonus[Bonus %],0)*D17 -> 30314.12 | F17: =D17+E17 -> 189862.12 | G17: =_xlfn.XLOOKUP(D17,$G$56:$G$60,$H$56:$H$60,,-1)*D17 -> 0 | H17: =SUM(F17:G17) -> 189862.12 | J17: {=TranslateMe(87)} -> Search Mode | L17: search_mode
B18: 1992 | C18: René Felber | D18: 157848 | E18: =_xlfn.XLOOKUP(tbl_Presidents[[#This Row],[Nom / Name]],Tableau_bonus[Nom],Tableau_bonus[Bonus %],0)*D18 -> 28412.64 | F18: =D18+E18 -> 186260.64 | G18: =_xlfn.XLOOKUP(D18,$G$56:$G$60,$H$56:$H$60,,-1)*D18 -> 0 | H18: =SUM(F18:G18) -> 186260.64 | J18: Micheline Calmy-Rey | K18: Micheline Calmy-Rey
B19: 1993 | C19: Adolf Ogi | D19: 160322 | E19: =_xlfn.XLOOKUP(tbl_Presidents[[#This Row],[Nom / Name]],Tableau_bonus[Nom],Tableau_bonus[Bonus %],0)*D19 -> 28857.96 | F19: =D19+E19 -> 189179.96 | G19: =_xlfn.XLOOKUP(D19,$G$56:$G$60,$H$56:$H$60,,-1)*D19 -> 8016.1 | H19: =SUM(F19:G19) -> 197196.06 | J19: Année | K19: Année | L19: 1 Search from first to last (top to bottom or left to right) — default
B20: 1994 | C20: Kaspar Villiger | D20: 157868 | E20: =_xlfn.XLOOKUP(tbl_Presidents[[#This Row],[Nom / Name]],Tableau_bonus[Nom],Tableau_bonus[Bonus %],0)*D20 -> 26837.56 | F20: =D20+E20 -> 184705.56 | G20: =_xlfn.XLOOKUP(D20,$G$56:$G$60,$H$56:$H$60,,-1)*D20 -> 0 | H20: =SUM(F20:G20) -> 184705.56 | J20: =_xlfn.XLOOKUP($J$18,tbl_Presidents[Nom / Name],tbl_Presidents[Année / Year]) -> 2007 | K20: =_xlfn.XLOOKUP($K$18,tbl_Presidents[Nom / Name],tbl_Presidents[Année / Year],,0,-1) -> 2011 | L20: -1 Search from last to first (bottom to top or right to left)
B21: 1995 | C21: Jean-Pascal Delamuraz | D21: 161565 | E21: =_xlfn.XLOOKUP(tbl_Presidents[[#This Row],[Nom / Name]],Tableau_bonus[Nom],Tableau_bonus[Bonus %],0)*D21 -> 37159.95 | F21: =D21+E21 -> 198724.95 | G21: =_xlfn.XLOOKUP(D21,$G$56:$G$60,$H$56:$H$60,,-1)*D21 -> 8078.25 | H21: =SUM(F21:G21) -> 206803.2
B22: 1996 | C22: Arnold Koller | D22: 164816 | E22: =_xlfn.XLOOKUP(tbl_Presidents[[#This Row],[Nom / Name]],Tableau_bonus[Nom],Tableau_bonus[Bonus %],0)*D22 -> 32963.2 | F22: =D22+E22 -> 197779.2 | G22: =_xlfn.XLOOKUP(D22,$G$56:$G$60,$H$56:$H$60,,-1)*D22 -> 8240.8 | H22: =SUM(F22:G22) -> 206020
B23: 1997 | C23: Arnold Koller | D23: 159673 | E23: =_xlfn.XLOOKUP(tbl_Presidents[[#This Row],[Nom / Name]],Tableau_bonus[Nom],Tableau_bonus[Bonus %],0)*D23 -> 31934.6 | F23: =D23+E23 -> 191607.6 | G23: =_xlfn.XLOOKUP(D23,$G$56:$G$60,$H$56:$H$60,,-1)*D23 -> 0 | H23: =SUM(F23:G23) -> 191607.6 | J23: {=TranslateMe(88)} -> 2 way XLOOKUP | M23: {=TranslateMe(88)} -> 2 way XLOOKUP
B24: 1998 | C24: Flavio Cotti | D24: 165048 | E24: =_xlfn.XLOOKUP(tbl_Presidents[[#This Row],[Nom / Name]],Tableau_bonus[Nom],Tableau_bonus[Bonus %],0)*D24 -> 31359.12 | F24: =D24+E24 -> 196407.12 | G24: =_xlfn.XLOOKUP(D24,$G$56:$G$60,$H$56:$H$60,,-1)*D24 -> 8252.4 | H24: =SUM(F24:G24) -> 204659.52 | J24: Jean-Pascal Delamuraz | M24: Fritz Honegger | N24: Jean-Pascal Delamuraz | O24: Elisabeth Kopp
B25: 1999 | C25: Ruth Dreifuss | D25: 166454 | E25: =_xlfn.XLOOKUP(tbl_Presidents[[#This Row],[Nom / Name]],Tableau_bonus[Nom],Tableau_bonus[Bonus %],0)*D25 -> 36619.88 | F25: =D25+E25 -> 203073.88 | G25: =_xlfn.XLOOKUP(D25,$G$56:$G$60,$H$56:$H$60,,-1)*D25 -> 8322.7 | H25: =SUM(F25:G25) -> 211396.58 | J25: Base+Bonus | M25: Base+Bonus
B26: 2000 | C26: Adolf Ogi | D26: 160740 | E26: =_xlfn.XLOOKUP(tbl_Presidents[[#This Row],[Nom / Name]],Tableau_bonus[Nom],Tableau_bonus[Bonus %],0)*D26 -> 28933.2 | F26: =D26+E26 -> 189673.2 | G26: =_xlfn.XLOOKUP(D26,$G$56:$G$60,$H$56:$H$60,,-1)*D26 -> 8037 | H26: =SUM(F26:G26) -> 197710.2 | J26: {=_xlfn.XLOOKUP($J$24,$C$6:$C$50,_xlfn.XLOOKUP($J$25,$D$5:$F$5,$D$6:$F$50))} -> 190738.56 | M26: {=_xlfn.XLOOKUP(M24:O24,$C$6:$C$50,_xlfn.XLOOKUP($M$25,$D$5:$F$5,$D$6:$F$50))} -> 189530 | N26: 190738.56 | O26: 189090.33
B27: 2001 | C27: Moritz Leuenberger | D27: 162411 | E27: =_xlfn.XLOOKUP(tbl_Presidents[[#This Row],[Nom / Name]],Tableau_bonus[Nom],Tableau_bonus[Bonus %],0)*D27 -> 40602.75 | F27: =D27+E27 -> 203013.75 | G27: =_xlfn.XLOOKUP(D27,$G$56:$G$60,$H$56:$H$60,,-1)*D27 -> 8120.55 | H27: =SUM(F27:G27) -> 211134.3 | J27: =_xlfn.FORMULATEXT(J26) -> =RECHERCHEX($J$24;$C$6:$C$50;RECHERCHEX($J$25;$D$5:$F$5;$D$6:$F$50)) | M27: =_xlfn.FORMULATEXT(M26) -> =RECHERCHEX(M24:O24;$C$6:$C$50;RECHERCHEX($M$25;$D$5:$F$5;$D$6:$F$50))
B28: 2002 | C28: Kaspar Villiger | D28: 166104 | E28: =_xlfn.XLOOKUP(tbl_Presidents[[#This Row],[Nom / Name]],Tableau_bonus[Nom],Tableau_bonus[Bonus %],0)*D28 -> 28237.68 | F28: =D28+E28 -> 194341.68 | G28: =_xlfn.XLOOKUP(D28,$G$56:$G$60,$H$56:$H$60,,-1)*D28 -> 8305.2 | H28: =SUM(F28:G28) -> 202646.88
B29: 2003 | C29: Pascal Couchepin | D29: 171827 | E29: =_xlfn.XLOOKUP(tbl_Presidents[[#This Row],[Nom / Name]],Tableau_bonus[Nom],Tableau_bonus[Bonus %],0)*D29 -> 42956.75 | F29: =D29+E29 -> 214783.75 | G29: =_xlfn.XLOOKUP(D29,$G$56:$G$60,$H$56:$H$60,,-1)*D29 -> 13746.16 | H29: =SUM(F29:G29) -> 228529.91 | J29: {=TranslateMe(95)} -> XLOOKUP with 2 lookup values
B30: 2004 | C30: Joseph Deiss | D30: 170496 | E30: =_xlfn.XLOOKUP(tbl_Presidents[[#This Row],[Nom / Name]],Tableau_bonus[Nom],Tableau_bonus[Bonus %],0)*D30 -> 40919.04 | F30: =D30+E30 -> 211415.04 | G30: =_xlfn.XLOOKUP(D30,$G$56:$G$60,$H$56:$H$60,,-1)*D30 -> 13639.68 | H30: =SUM(F30:G30) -> 225054.72 | J30: Pascal Couchepin
B31: 2005 | C31: Samuel Schmid | D31: 170900 | E31: =_xlfn.XLOOKUP(tbl_Presidents[[#This Row],[Nom / Name]],Tableau_bonus[Nom],Tableau_bonus[Bonus %],0)*D31 -> 41016 | F31: =D31+E31 -> 211916 | G31: =_xlfn.XLOOKUP(D31,$G$56:$G$60,$H$56:$H$60,,-1)*D31 -> 13672 | H31: =SUM(F31:G31) -> 225588 | J31: 2008
B32: 2006 | C32: Moritz Leuenberger | D32: 163754 | E32: =_xlfn.XLOOKUP(tbl_Presidents[[#This Row],[Nom / Name]],Tableau_bonus[Nom],Tableau_bonus[Bonus %],0)*D32 -> 40938.5 | F32: =D32+E32 -> 204692.5 | G32: =_xlfn.XLOOKUP(D32,$G$56:$G$60,$H$56:$H$60,,-1)*D32 -> 8187.7 | H32: =SUM(F32:G32) -> 212880.2 | J32: {=_xlfn.XLOOKUP($J$30&$J$31,tbl_Presidents[Nom / Name]&tbl_Presidents[Année / Year],tbl_Presidents[Total])} -> 233984.24 | K32: {=_xlfn.XLOOKUP(1,(tbl_Presidents[Nom / Name]=$J$30)*(tbl_Presidents[Année / Year]=$J$31),tbl_Presidents[Total])} -> 233984.24 | L32: =_xlfn.FORMULATEXT(K32) -> =RECHERCHEX(1;(tbl_Presidents[Nom / Name]=$J$30)*(tbl_Presidents[Année / Year]=$J$31);tbl_Presidents[Total])
B33: 2007 | C33: Micheline Calmy-Rey | D33: 176919 | E33: =_xlfn.XLOOKUP(tbl_Presidents[[#This Row],[Nom / Name]],Tableau_bonus[Nom],Tableau_bonus[Bonus %],0)*D33 -> 40691.37 | F33: =D33+E33 -> 217610.37 | G33: =_xlfn.XLOOKUP(D33,$G$56:$G$60,$H$56:$H$60,,-1)*D33 -> 14153.52 | H33: =SUM(F33:G33) -> 231763.89 | J33: =_xlfn.FORMULATEXT(J32) -> =RECHERCHEX($J$30&$J$31;tbl_Presidents[Nom / Name]&tbl_Presidents[Année / Year];tbl_Presidents[Total])
B34: 2008 | C34: Pascal Couchepin | D34: 175928 | E34: =_xlfn.XLOOKUP(tbl_Presidents[[#This Row],[Nom / Name]],Tableau_bonus[Nom],Tableau_bonus[Bonus %],0)*D34 -> 43982 | F34: =D34+E34 -> 219910 | G34: =_xlfn.XLOOKUP(D34,$G$56:$G$60,$H$56:$H$60,,-1)*D34 -> 14074.24 | H34: =SUM(F34:G34) -> 233984.24
B35: 2009 | C35: Hans-Rudolf Merz | D35: 174592 | E35: =_xlfn.XLOOKUP(tbl_Presidents[[#This Row],[Nom / Name]],Tableau_bonus[Nom],Tableau_bonus[Bonus %],0)*D35 -> 34918.4 | F35: =D35+E35 -> 209510.4 | G35: =_xlfn.XLOOKUP(D35,$G$56:$G$60,$H$56:$H$60,,-1)*D35 -> 13967.36 | H35: =SUM(F35:G35) -> 223477.76 | J35: {=TranslateMe(89)} -> TOP 3 | M35: {=TranslateMe(90)} -> Summing with XLOOKUP
B36: 2010 | C36: Doris Leuthard | D36: 177180 | E36: =_xlfn.XLOOKUP(tbl_Presidents[[#This Row],[Nom / Name]],Tableau_bonus[Nom],Tableau_bonus[Bonus %],0)*D36 -> 33664.2 | F36: =D36+E36 -> 210844.2 | G36: =_xlfn.XLOOKUP(D36,$G$56:$G$60,$H$56:$H$60,,-1)*D36 -> 14174.4 | H36: =SUM(F36:G36) -> 225018.6 | J36: {=LARGE($H$6:$H$50,_xlfn.SEQUENCE(3))} -> 254240.88 | K36: {=_xlfn.XLOOKUP(_xlfn.ANCHORARRAY($J$36),$H$6:$H$50,tbl_Presidents[Nom / Name]:tbl_Presidents[Base])} -> Ignazio Cassis | M36: 1990
B37: 2011 | C37: Micheline Calmy-Rey | D37: 166802 | E37: =_xlfn.XLOOKUP(tbl_Presidents[[#This Row],[Nom / Name]],Tableau_bonus[Nom],Tableau_bonus[Bonus %],0)*D37 -> 38364.46 | F37: =D37+E37 -> 205166.46 | G37: =_xlfn.XLOOKUP(D37,$G$56:$G$60,$H$56:$H$60,,-1)*D37 -> 8340.1 | H37: =SUM(F37:G37) -> 213506.56 | J37: 239893.56 | K37: Doris Leuthard | M37: 2000
B38: 2012 | C38: Eveline Widmer-Schlumpf | D38: 174000 | E38: =_xlfn.XLOOKUP(tbl_Presidents[[#This Row],[Nom / Name]],Tableau_bonus[Nom],Tableau_bonus[Bonus %],0)*D38 -> 31320 | F38: =D38+E38 -> 205320 | G38: =_xlfn.XLOOKUP(D38,$G$56:$G$60,$H$56:$H$60,,-1)*D38 -> 13920 | H38: =SUM(F38:G38) -> 219240 | J38: 236670.2 | K38: Alain Berset | M38: =SUM(_xlfn.XLOOKUP(M36,tbl_Presidents[Année / Year],tbl_Presidents[Total]):_xlfn.XLOOKUP(M37,tbl_Presidents[Année / Year],tbl_Presidents[Total])) -> 2164285.5 | N38: =SUMIFS(tbl_Presidents[Total],tbl_Presidents[Année / Year],">=1990",tbl_Presidents[Année / Year],"< 2001") -> 2164285.5
B39: 2013 | C39: Ueli Maurer | D39: 179370 | E39: =_xlfn.XLOOKUP(tbl_Presidents[[#This Row],[Nom / Name]],Tableau_bonus[Nom],Tableau_bonus[Bonus %],0)*D39 -> 30492.9 | F39: =D39+E39 -> 209862.9 | G39: =_xlfn.XLOOKUP(D39,$G$56:$G$60,$H$56:$H$60,,-1)*D39 -> 14349.6 | H39: =SUM(F39:G39) -> 224212.5
B40: 2014 | C40: Didier Burkhalter | D40: 176792 | E40: =_xlfn.XLOOKUP(tbl_Presidents[[#This Row],[Nom / Name]],Tableau_bonus[Nom],Tableau_bonus[Bonus %],0)*D40 -> 24750.88 | F40: =D40+E40 -> 201542.88 | G40: =_xlfn.XLOOKUP(D40,$G$56:$G$60,$H$56:$H$60,,-1)*D40 -> 14143.36 | H40: =SUM(F40:G40) -> 215686.24 | K40: =_xlfn.FORMULATEXT(K36) -> =RECHERCHEX($J$36#;$H$6:$H$50;tbl_Presidents[Nom / Name]:tbl_Presidents[Base])
B41: 2015 | C41: Simonetta Sommaruga | D41: 182550 | E41: =_xlfn.XLOOKUP(tbl_Presidents[[#This Row],[Nom / Name]],Tableau_bonus[Nom],Tableau_bonus[Bonus %],0)*D41 -> 25557 | F41: =D41+E41 -> 208107 | G41: =_xlfn.XLOOKUP(D41,$G$56:$G$60,$H$56:$H$60,,-1)*D41 -> 18255 | H41: =SUM(F41:G41) -> 226362 | K41: {=TranslateMe(91)} -> Notice that if the 1st argument of XLOOKUP is a matrix, only one column is returned
B42: 2016 | C42: Johann Schneider-Ammann | D42: 173832 | E42: =_xlfn.XLOOKUP(tbl_Presidents[[#This Row],[Nom / Name]],Tableau_bonus[Nom],Tableau_bonus[Bonus %],0)*D42 -> 38243.04 | F42: =D42+E42 -> 212075.04 | G42: =_xlfn.XLOOKUP(D42,$G$56:$G$60,$H$56:$H$60,,-1)*D42 -> 13906.56 | H42: =SUM(F42:G42) -> 225981.6
B43: 2017 | C43: Doris Leuthard | D43: 185964 | E43: =_xlfn.XLOOKUP(tbl_Presidents[[#This Row],[Nom / Name]],Tableau_bonus[Nom],Tableau_bonus[Bonus %],0)*D43 -> 35333.16 | F43: =D43+E43 -> 221297.16 | G43: =_xlfn.XLOOKUP(D43,$G$56:$G$60,$H$56:$H$60,,-1)*D43 -> 18596.4 | H43: =SUM(F43:G43) -> 239893.56 | J43: {=TranslateMe(92)} -> Approximate match | N43: match_mode
B44: 2018 | C44: Alain Berset | D44: 180820 | E44: =_xlfn.XLOOKUP(tbl_Presidents[[#This Row],[Nom / Name]],Tableau_bonus[Nom],Tableau_bonus[Bonus %],0)*D44 -> 36164 | F44: =D44+E44 -> 216984 | G44: =_xlfn.XLOOKUP(D44,$G$56:$G$60,$H$56:$H$60,,-1)*D44 -> 18082 | H44: =SUM(F44:G44) -> 235066 | J44: Johann Schneider-Ammann | K44: {=_xlfn.XLOOKUP($J$44:$J$46,$C$6:$C$50,$D$6:$D$50,,,-1)} -> 173832 | L44: {=_xlfn.XLOOKUP(_xlfn.ANCHORARRAY($K$44),$G$56:$G$60,$H$56:$H$60,,-1)} -> 0.08 | N44: 0 Exact match (default). If no exact match is found, returns #N/A.
B45: 2019 | C45: Ueli Maurer | D45: 182058 | E45: =_xlfn.XLOOKUP(tbl_Presidents[[#This Row],[Nom / Name]],Tableau_bonus[Nom],Tableau_bonus[Bonus %],0)*D45 -> 30949.86 | F45: =D45+E45 -> 213007.86 | G45: =_xlfn.XLOOKUP(D45,$G$56:$G$60,$H$56:$H$60,,-1)*D45 -> 18205.8 | H45: =SUM(F45:G45) -> 231213.66 | J45: Jean-Pascal Delamuraz | K45: 161565 | L45: 0.05 | N45: -1 Exact match or next smaller item.
B46: 2020 | C46: Simonetta Sommaruga | D46: 181800 | E46: =_xlfn.XLOOKUP(tbl_Presidents[[#This Row],[Nom / Name]],Tableau_bonus[Nom],Tableau_bonus[Bonus %],0)*D46 -> 25452 | F46: =D46+E46 -> 207252 | G46: =_xlfn.XLOOKUP(D46,$G$56:$G$60,$H$56:$H$60,,-1)*D46 -> 18180 | H46: =SUM(F46:G46) -> 225432 | J46: Viola Amherd | K46: 181680 | L46: 0.1 | N46: 1 Exact match or next larger item.
B47: 2021 | C47: Guy Parmelin | D47: 174600 | E47: =_xlfn.XLOOKUP(tbl_Presidents[[#This Row],[Nom / Name]],Tableau_bonus[Nom],Tableau_bonus[Bonus %],0)*D47 -> 41904 | F47: =D47+E47 -> 216504 | G47: =_xlfn.XLOOKUP(D47,$G$56:$G$60,$H$56:$H$60,,-1)*D47 -> 13968 | H47: =SUM(F47:G47) -> 230472 | L47: =_xlfn.FORMULATEXT(L44) -> =RECHERCHEX($K$44#;$G$56:$G$60;$H$56:$H$60;;-1) | N47: 2 Wildcard match. Supports *, ?, and ~ in the lookup value.
B48: 2022 | C48: Ignazio Cassis | D48: 189732 | E48: =_xlfn.XLOOKUP(tbl_Presidents[[#This Row],[Nom / Name]],Tableau_bonus[Nom],Tableau_bonus[Bonus %],0)*D48 -> 45535.68 | F48: =D48+E48 -> 235267.68 | G48: =_xlfn.XLOOKUP(D48,$G$56:$G$60,$H$56:$H$60,,-1)*D48 -> 18973.2 | H48: =SUM(F48:G48) -> 254240.88
B49: 2023 | C49: Alain Berset | D49: 182054 | E49: =_xlfn.XLOOKUP(tbl_Presidents[[#This Row],[Nom / Name]],Tableau_bonus[Nom],Tableau_bonus[Bonus %],0)*D49 -> 36410.8 | F49: =D49+E49 -> 218464.8 | G49: =_xlfn.XLOOKUP(D49,$G$56:$G$60,$H$56:$H$60,,-1)*D49 -> 18205.4 | H49: =SUM(F49:G49) -> 236670.2
B50: 2024 | C50: Viola Amherd | D50: 181680 | E50: =_xlfn.XLOOKUP(tbl_Presidents[[#This Row],[Nom / Name]],Tableau_bonus[Nom],Tableau_bonus[Bonus %],0)*D50 -> 36336 | F50: =D50+E50 -> 218016 | G50: =_xlfn.XLOOKUP(D50,$G$56:$G$60,$H$56:$H$60,,-1)*D50 -> 18168 | H50: =SUM(F50:G50) -> 236184 | J50: {=TranslateMe(93)} -> Sum of all bonuses for the TOP 3
J51: {=SUM(_xlfn.XLOOKUP(_xlfn.ANCHORARRAY($J$36),tbl_Presidents[Total],tbl_Presidents[[Extra Bonus ]]),_xlfn.XLOOKUP(_xlfn.ANCHORARRAY($J$36),tbl_Presidents[Total],tbl_Presidents[Bonus]))} -> 173054.64
B55: ID | C55: Bonus % | D55: Nom | G55: Extra Bonus Ranges
B56: 1980 | C56: 0.22 | D56: Georges-André Chevallaz | G56: 150000 | H56: 0
B57: 1981 | C57: 0.25 | D57: Kurt Furgler | G57: 160000 | H57: 0.05
B58: 1982 | C58: 0.25 | D58: Fritz Honegger | G58: 170000 | H58: 0.08
B59: 1983 | C59: 0.25 | D59: Pierre Aubert | G59: 180000 | H59: 0.1
B60: 1984 | C60: 0.25 | D60: Leon Schlumpf | G60: 190000 | H60: 0.15
B61: 1985 | C61: 0.24 | D61: Alphons Egli
B62: 1986 | C62: 0.24 | D62: Alphons Egli
B63: 1987 | C63: 0.23 | D63: Otto Stich
B64: 1988 | C64: 0.23 | D64: Jean-Pascal Delamuraz
B65: 1989 | C65: 0.21 | D65: Elisabeth Kopp
B66: 1990 | C66: 0.2 | D66: Arnold Koller
B67: 1991 | C67: 0.19 | D67: Flavio Cotti
B68: 1992 | C68: 0.18 | D68: René Felber
B69: 1993 | C69: 0.18 | D69: Adolf Ogi
B70: 1994 | C70: 0.17 | D70: Kaspar Villiger
B71: 1995 | C71: 0.14 | D71: Jean-Pascal Delamuraz
B72: 1996 | C72: 0.14 | D72: Arnold Koller
... B100: 2024 | C100: 0.2 | D100: Viola Amherd

Sheet 78. TABLE MANIP.
A1: #VALUE! | C1: {=TranslateMe(31)} -> MATRIX HANDLING
B2: CAT | C2: ENG | D2: FR | F2: CAT | G2: ENG | H2: FR | J2: CAT | K2: ENG | L2: FR
B3: 1 | C3: FILTER | D3: FILTRE | F3: 2 | G3: XLOOKUP | H3: RECHERCHEX | J3: 4 | K3: IMAGE | L3: IMAGE
B4: 1 | C4: SORT | D4: TRIER | F4: 2 | G4: XMATCH | H4: EQUIVX | J4: 4 | K4: TEXTAFTER | L4: TEXTE.APRES
B5: 1 | C5: SORTBY | D5: TRIERPAR | J5: 4 | K5: TEXTBEFORE | L5: TEXTE.AVANT
B6: 1 | C6: UNIQUE | D6: UNIQUE | J6: 4 | K6: STOCKHISTORY | L6: HISTORIQUE.ACTIONS
B7: 1 | C7: SEQUENCE | D7: SEQUENCE | F7: CAT | G7: ENG | H7: FR | J7: 4 | K7: ISOMITTED | L7: ISOMITTED
B8: 1 | C8: RANDARRAY | D8: TABLEAU.ALEA | F8: 3 | G8: LET | H8: LET
B9: 1 | C9: TEXTJOIN | D9: JOINDRE.TEXTE | F9: 3 | G9: LAMBDA | H9: LAMBDA
B10: 1 | C10: ARRAYTOTEXT | D10: TABLEAU.EN.TEXTE | F10: 3 | G10: BYROW | H10: PAR.LIGNE | J10: CAT | K10: ENG | L10: FR
B11: 1 | C11: EXPAND | D11: ETENDRE | F11: 3 | G11: BYCOL | H11: PAR.COLONNE | J11: 5 | K11: IFERROR | L11: SIERREUR
B12: 1 | C12: TOCOL | D12: DANSCOLONNE | F12: 3 | G12: MAKEARRAY | H12: CREERTABLEAU | J12: 5 | K12: IFNA | L12: SI.NA
B13: 1 | C13: TOROW | D13: DANSLIGNE | F13: 3 | G13: MAP | H13: CARTOGRAPHIE
B14: 1 | C14: WRAPCOLS | D14: ORGA.COLS | F14: 3 | G14: REDUCE | H14: REDUCE
B15: 1 | C15: WRAPROWS | D15: ORGA.LIGNES | F15: 3 | G15: SCAN | H15: SCAN
B16: 1 | C16: CHOOSECOLS | D16: CHOISIRCOLS | F16: 3 | G16: TEXTSPLIT | H16: FRACTIONNER.TEXTE
B17: 1 | C17: CHOOSEROWS | D17: CHOISIRLIGNES | F17: 3 | G17: TAKE | H17: PRENDRE
B18: 1 | C18: VSTACK | D18: ASSEMB.V | F18: 3 | G18: DROP | H18: SUPPRIMER
B19: 1 | C19: HSTACK | D19: ASSEMB.H
B21: {=Translatefct(160,0)} -> HSTACK | D21: {=Translatefct(160,1)} -> Horizontally stacks arrays or ranges.
B22: =_xlfn.FORMULATEXT(B23) -> =ASSEMB.H(B3:D4;F3:H4;F8:H9;J3:L4;J11:L12)
B23: {=_xlfn.HSTACK(B3:D4,F3:H4,F8:H9,J3:L4,J11:L12)} -> 1 | C23: FILTER | D23: FILTRE | E23: 2 | F23: XLOOKUP | G23: RECHERCHEX | H23: 3 | I23: LET | J23: LET | K23: 4 | L23: IMAGE | M23: IMAGE | N23: 5 | O23: IFERROR | P23: SIERREUR
B24: 1 | C24: SORT | D24: TRIER | E24: 2 | F24: XMATCH | G24: EQUIVX | H24: 3 | I24: LAMBDA | J24: LAMBDA | K24: 4 | L24: TEXTAFTER | M24: TEXTE.APRES | N24: 5 | O24: IFNA | P24: SI.NA
B26: {=Translatefct(150,0)} -> VSTACK | F26: {=Translatefct(280,0)} -> TAKE | J26: {=Translatefct(970,0)} -> DROP | N26: {=Translatefct(130,0)} -> CHOOSECOLS
B27: {=Translatefct(150,1)} -> Vertically stacks arrays or ranges. | F27: {=Translatefct(280,1)} -> Returns a specified number of rows or columns from the start or end of an array. | J27: {=Translatefct(970,1)} -> Excludes a specified number of rows or columns from the start or end of an array. | N27: {=Translatefct(130,1)} -> Selects specific columns from an array.
B28: =_xlfn.FORMULATEXT(B29) -> =ASSEMB.V(B2:D19;F3:H4;F8:H18;J3:L7;J11:L12) | F28: =_xlfn.FORMULATEXT(F29) -> =PRENDRE(B29#;10) | J28: =_xlfn.FORMULATEXT(J29) -> =EXCLURE(B29#;30;1) | N28: =_xlfn.FORMULATEXT(N29) -> =CHOISIRCOLS($B$29#;2)
B29: {=_xlfn.VSTACK(B2:D19,F3:H4,F8:H18,J3:L7,J11:L12)} -> CAT | C29: ENG | D29: FR | F29: {=_xlfn.TAKE(_xlfn.ANCHORARRAY(B29),10)} -> CAT | G29: ENG | H29: FR | J29: {=_xlfn.DROP(_xlfn.ANCHORARRAY(B29),30,1)} -> DROP | K29: SUPPRIMER | N29: {=_xlfn.CHOOSECOLS(_xlfn.ANCHORARRAY($B$29),2)} -> ENG | P29: {=Translatefct(140,0)} -> CHOOSEROWS
B30: 1 | C30: FILTER | D30: FILTRE | F30: 1 | G30: FILTER | H30: FILTRE | J30: IMAGE | K30: IMAGE | N30: FILTER | P30: {=Translatefct(140,1)} -> Selects specific rows from an array.
B31: 1 | C31: SORT | D31: TRIER | F31: 1 | G31: SORT | H31: TRIER | J31: TEXTAFTER | K31: TEXTE.APRES | N31: SORT | P31: =_xlfn.FORMULATEXT(P32) -> =CHOISIRLIGNES($B$29#;10;15;20;25)
B32: 1 | C32: SORTBY | D32: TRIERPAR | F32: 1 | G32: SORTBY | H32: TRIERPAR | J32: TEXTBEFORE | K32: TEXTE.AVANT | N32: SORTBY | P32: {=_xlfn.CHOOSEROWS(_xlfn.ANCHORARRAY($B$29),10,15,20,25)} -> 1 | Q32: EXPAND | R32: ETENDRE
B33: 1 | C33: UNIQUE | D33: UNIQUE | F33: 1 | G33: UNIQUE | H33: UNIQUE | J33: STOCKHISTORY | K33: HISTORIQUE.ACTIONS | N33: UNIQUE | P33: 1 | Q33: CHOOSECOLS | R33: CHOISIRCOLS
B34: 1 | C34: SEQUENCE | D34: SEQUENCE | F34: 1 | G34: SEQUENCE | H34: SEQUENCE | J34: ISOMITTED | K34: ISOMITTED | N34: SEQUENCE | P34: 2 | Q34: XMATCH | R34: EQUIVX
B35: 1 | C35: RANDARRAY | D35: TABLEAU.ALEA | F35: 1 | G35: RANDARRAY | H35: TABLEAU.ALEA | J35: IFERROR | K35: SIERREUR | N35: RANDARRAY | P35: 3 | Q35: MAKEARRAY | R35: CREERTABLEAU
B36: 1 | C36: TEXTJOIN | D36: JOINDRE.TEXTE | F36: 1 | G36: TEXTJOIN | H36: JOINDRE.TEXTE | J36: IFNA | K36: SI.NA | N36: TEXTJOIN
B37: 1 | C37: ARRAYTOTEXT | D37: TABLEAU.EN.TEXTE | F37: 1 | G37: ARRAYTOTEXT | H37: TABLEAU.EN.TEXTE | N37: ARRAYTOTEXT
B38: 1 | C38: EXPAND | D38: ETENDRE | F38: 1 | G38: EXPAND | H38: ETENDRE | N38: EXPAND
B39: 1 | C39: TOCOL | D39: DANSCOLONNE | N39: TOCOL
B40: 1 | C40: TOROW | D40: DANSLIGNE | F40: =_xlfn.FORMULATEXT(F41) -> =PRENDRE($F$29#;;-2) | N40: TOROW
B41: 1 | C41: WRAPCOLS | D41: ORGA.COLS | F41: {=_xlfn.TAKE(_xlfn.ANCHORARRAY($F$29),,-2)} -> ENG | G41: FR | N41: WRAPCOLS
B42: 1 | C42: WRAPROWS | D42: ORGA.LIGNES | F42: FILTER | G42: FILTRE | N42: WRAPROWS
B43: 1 | C43: CHOOSECOLS | D43: CHOISIRCOLS | F43: SORT | G43: TRIER | N43: CHOOSECOLS
B44: 1 | C44: CHOOSEROWS | D44: CHOISIRLIGNES | F44: SORTBY | G44: TRIERPAR | N44: CHOOSEROWS
B45: 1 | C45: VSTACK | D45: ASSEMB.V | F45: UNIQUE | G45: UNIQUE | N45: VSTACK
B46: 1 | C46: HSTACK | D46: ASSEMB.H | F46: SEQUENCE | G46: SEQUENCE | N46: HSTACK
B47: 2 | C47: XLOOKUP | D47: RECHERCHEX | F47: RANDARRAY | G47: TABLEAU.ALEA | N47: XLOOKUP
B48: 2 | C48: XMATCH | D48: EQUIVX | F48: TEXTJOIN | G48: JOINDRE.TEXTE | N48: XMATCH
B49: 3 | C49: LET | D49: LET | F49: ARRAYTOTEXT | G49: TABLEAU.EN.TEXTE | N49: LET
B50: 3 | C50: LAMBDA | D50: LAMBDA | F50: EXPAND | G50: ETENDRE | N50: LAMBDA
B51: 3 | C51: BYROW | D51: PAR.LIGNE | N51: BYROW
B52: 3 | C52: BYCOL | D52: PAR.COLONNE | N52: BYCOL
B53: 3 | C53: MAKEARRAY | D53: CREERTABLEAU | F53: =_xlfn.FORMULATEXT(F54) -> =PRENDRE($F$29#;-3) | N53: MAKEARRAY
B54: 3 | C54: MAP | D54: CARTOGRAPHIE | F54: {=_xlfn.TAKE(_xlfn.ANCHORARRAY($F$29),-3)} -> 1 | G54: TEXTJOIN | H54: JOINDRE.TEXTE | N54: MAP
B55: 3 | C55: REDUCE | D55: REDUCE | F55: 1 | G55: ARRAYTOTEXT | H55: TABLEAU.EN.TEXTE | N55: REDUCE
B56: 3 | C56: SCAN | D56: SCAN | F56: 1 | G56: EXPAND | H56: ETENDRE | N56: SCAN
B57: 3 | C57: TEXTSPLIT | D57: FRACTIONNER.TEXTE | N57: TEXTSPLIT
B58: 3 | C58: TAKE | D58: PRENDRE | F58: =_xlfn.FORMULATEXT(F59) -> =ASSEMB.V(F54#;{"---"."---"."---"}) | N58: TAKE
B59: 3 | C59: DROP | D59: SUPPRIMER | F59: {=_xlfn.VSTACK(_xlfn.ANCHORARRAY(F54),{"---","---","---"})} -> 1 | G59: TEXTJOIN | H59: JOINDRE.TEXTE | N59: DROP
B60: 4 | C60: IMAGE | D60: IMAGE | F60: 1 | G60: ARRAYTOTEXT | H60: TABLEAU.EN.TEXTE | N60: IMAGE
B61: 4 | C61: TEXTAFTER | D61: TEXTE.APRES | F61: 1 | G61: EXPAND | H61: ETENDRE | N61: TEXTAFTER
B62: 4 | C62: TEXTBEFORE | D62: TEXTE.AVANT | F62: --- | G62: --- | H62: --- | N62: TEXTBEFORE
B63: 4 | C63: STOCKHISTORY | D63: HISTORIQUE.ACTIONS | N63: STOCKHISTORY
B64: 4 | C64: ISOMITTED | D64: ISOMITTED | N64: ISOMITTED
B65: 5 | C65: IFERROR | D65: SIERREUR | N65: IFERROR
B66: 5 | C66: IFNA | D66: SI.NA | N66: IFNA
F68: {=Translatefct(100,0)} -> TOROW
F69: {=Translatefct(100,1)} -> Transforms a range or array into a single row.
B70: CAT | C70: ENG | D70: FR | F70: =_xlfn.FORMULATEXT(F71) -> =DANSLIGNE(C71:D87)
B71: 1 | C71: FILTER | D71: FILTRE | F71: {=_xlfn.TOROW(C71:D87)} -> FILTER | G71: FILTRE | H71: SORT | I71: TRIER | J71: SORTBY | K71: TRIERPAR | L71: UNIQUE | M71: UNIQUE | N71: SEQUENCE | O71: SEQUENCE | P71: RANDARRAY | Q71: TABLEAU.ALEA | R71: TEXTJOIN | S71: JOINDRE.TEXTE | T71: ARRAYTOTEXT | U71: TABLEAU.EN.TEXTE | V71: EXPAND | W71: ETENDRE | X71: TOCOL | Y71: DANSCOLONNE | Z71: TOROW | AA71: DANSLIGNE | AB71: WRAPCOLS | AC71: ORGA.COLS | AD71: WRAPROWS | AE71: ORGA.LIGNES | AF71: CHOOSECOLS | AG71: CHOISIRCOLS | AH71: CHOOSEROWS | AI71: CHOISIRLIGNES | AJ71: VSTACK | AK71: ASSEMB.V | AL71: HSTACK | AM71: ASSEMB.H
B72: 1 | C72: SORT | D72: TRIER
B73: 1 | C73: SORTBY | D73: TRIERPAR
B74: 1 | C74: UNIQUE | D74: UNIQUE | F74: {=Translatefct(110,0)} -> WRAPCOLS
B75: 1 | C75: SEQUENCE | D75: SEQUENCE | F75: {=Translatefct(110,1)} -> Arranges values from a single column into multiple columns.
B76: 1 | C76: RANDARRAY | D76: TABLEAU.ALEA | F76: =_xlfn.FORMULATEXT(F77) -> =ORGA.COLS(C71:C87;3;"---")
B77: 1 | C77: TEXTJOIN | D77: JOINDRE.TEXTE | F77: {=_xlfn.WRAPCOLS(C71:C87,3,"---")} -> FILTER | G77: UNIQUE | H77: TEXTJOIN | I77: TOCOL | J77: WRAPROWS | K77: VSTACK
B78: 1 | C78: ARRAYTOTEXT | D78: TABLEAU.EN.TEXTE | F78: SORT | G78: SEQUENCE | H78: ARRAYTOTEXT | I78: TOROW | J78: CHOOSECOLS | K78: HSTACK
B79: 1 | C79: EXPAND | D79: ETENDRE | F79: SORTBY | G79: RANDARRAY | H79: EXPAND | I79: WRAPCOLS | J79: CHOOSEROWS | K79: ---
B80: 1 | C80: TOCOL | D80: DANSCOLONNE
B81: 1 | C81: TOROW | D81: DANSLIGNE | F81: {=Translatefct(90,0)} -> TOCOL | I81: {=Translatefct(120,0)} -> WRAPROWS
B82: 1 | C82: WRAPCOLS | D82: ORGA.COLS | F82: {=Translatefct(90,1)} -> Transforms a range or array into a single column. | I82: {=Translatefct(120,1)} -> Arranges values from a single row into multiple rows.
B83: 1 | C83: WRAPROWS | D83: ORGA.LIGNES | F83: =_xlfn.FORMULATEXT(F84) -> =DANSCOL(ADRESSE(LIGNE(B71:D76);COLONNE(B71:D76);4)) | I83: =_xlfn.FORMULATEXT(I84) -> =ORGA.LIGNES($F$71#;2)
B84: 1 | C84: CHOOSECOLS | D84: CHOISIRCOLS | F84: {=_xlfn.TOCOL(ADDRESS(ROW(B71:D76),COLUMN(B71:D76),4))} -> B71 | I84: {=_xlfn.WRAPROWS(_xlfn.ANCHORARRAY($F$71),2)} -> FILTER | J84: FILTRE
B85: 1 | C85: CHOOSEROWS | D85: CHOISIRLIGNES | F85: C71 | I85: SORT | J85: TRIER
B86: 1 | C86: VSTACK | D86: ASSEMB.V | F86: D71 | I86: SORTBY | J86: TRIERPAR
B87: 1 | C87: HSTACK | D87: ASSEMB.H | F87: B72 | I87: UNIQUE | J87: UNIQUE
F88: C72 | I88: SEQUENCE | J88: SEQUENCE
F89: D72 | I89: RANDARRAY | J89: TABLEAU.ALEA
F90: B73 | I90: TEXTJOIN | J90: JOINDRE.TEXTE
F91: C73 | I91: ARRAYTOTEXT | J91: TABLEAU.EN.TEXTE
F92: D73 | I92: EXPAND | J92: ETENDRE
F93: B74 | I93: TOCOL | J93: DANSCOLONNE
F94: C74 | I94: TOROW | J94: DANSLIGNE
F95: D74 | I95: WRAPCOLS | J95: ORGA.COLS
F96: B75 | I96: WRAPROWS | J96: ORGA.LIGNES
F97: C75 | I97: CHOOSECOLS | J97: CHOISIRCOLS
F98: D75 | I98: CHOOSEROWS | J98: CHOISIRLIGNES
F99: B76 | I99: VSTACK | J99: ASSEMB.V
F100: C76 | I100: HSTACK | J100: ASSEMB.H
F101: D76

Sheet 70. FREQUENCY - RANK
A1: #VALUE! | C1: {=Translatefct(960,0)} -> RANK.EQ | G1: {=Translatefct(960,1)} -> Returns the rank of a number in a list of numbers | L1: {=Translatefct(950,0)} -> FREQUENCY | P1: {=Translatefct(950,1)} -> calculates how often values occur within a range of values, and then returns a vertical array of numbers.
B2: {=TranslateMe(177+COLUMN(B2))} -> Employee | C2: {=TranslateMe(177+COLUMN(C2))} -> Security level | D2: {=TranslateMe(177+COLUMN(D2))} -> Security ranking | E2: {=TranslateMe(177+COLUMN(E2))} -> Department | F2: {=TranslateMe(177+COLUMN(F2))} -> Region | G2: {=TranslateMe(177+COLUMN(G2))} -> Gender | H2: {=TranslateMe(177+COLUMN(H2))} -> Born in | I2: {=TranslateMe(177+COLUMN(I2))} -> Bonus | J2: {=TranslateMe(177+COLUMN(J2))} -> Bonus ranking
B3: James Willard | C3: 18 | D3: {=_xlfn.RANK.EQ(C3:C40,$C$3:$C$40)} -> 22 | E3: Sales | F3: Bern | G3: M | H3: 1968 | I3: 2508 | J3: {=_xlfn.RANK.EQ(I3:I40,$I$3:$I$40)} -> 32
B4: Brigitte Bond | C4: 10 | D4: 30 | E4: Sales | F4: Geneva | G4: F | H4: 1968 | I4: 2392 | J4: 33
B5: Daniel Garrett | C5: 28 | D5: 12 | E5: Finance | F5: Zurich | G5: M | H5: 1970 | I5: 7119 | J5: 10
B6: Walter Miller | C6: 5 | D6: 35 | E6: Sales | F6: Geneva | G6: M | H6: 1974 | I6: 1170 | J6: 35
B7: Gary Miller | C7: 44 | D7: 5 | E7: Finance | F7: Zurich | G7: M | H7: 1974 | I7: 950 | J7: 37
B8: Lukas Hofer | C8: 31 | D8: 9 | E8: Finance | F8: Lausanne | G8: M | H8: 1974 | I8: 5639 | J8: 14
B9: Peter Ramsy | C9: 9 | D9: 31 | E9: Sales | F9: Geneva | G9: M | H9: 1977 | I9: 3345 | J9: 25 | L9: Birth years distribution
B10: Richard Elliot | C10: 12 | D10: 28 | E10: Finance | F10: Zurich | G10: M | H10: 1977 | I10: 4883 | J10: 19 | L10: Matrix | M10: {=FREQUENCY(H3:H40,L11:L15)} -> 3 | N10: < 1970 (incl.)
B11: Corina Doyle | C11: 1 | D11: 38 | E11: Finance | F11: Zurich | G11: F | H11: 1980 | I11: 7575 | J11: 7 | L11: 1970 | M11: 6 | N11: Entre 1971 et 1980
B12: Ewan Thompson | C12: 22 | D12: 18 | E12: Sales | F12: Geneva | G12: M | H12: 1984 | I12: 9798 | J12: 1 | L12: 1980 | M12: 12 | N12: Entre 1981 et 1990
B13: Mike Saban | C13: 27 | D13: 13 | E13: Procurement | F13: Biel | G13: M | H13: 1984 | I13: 3578 | J13: 23 | L13: 1990 | M13: 6 | N13: Entre 1991 et 2000
B14: Robert Blume | C14: 6 | D14: 34 | E14: Finance | F14: Lausanne | G14: M | H14: 1984 | I14: 5815 | J14: 13 | L14: 2000 | M14: 9 | N14: Entre 2001 et 2010
B15: Robert Marquez | C15: 23 | D15: 17 | E15: Sales | F15: Bern | G15: M | H15: 1985 | I15: 4949 | J15: 17 | L15: 2010 | M15: 2 | N15: > 2010
B16: Andre Cooper | C16: 29 | D16: 11 | E16: Procurement | F16: Biel | G16: M | H16: 1985 | I16: 1121 | J16: 36 | M16: =_xlfn.FORMULATEXT(M10) -> =FREQUENCE(H3:H40;L11:L15)
B17: Betina Bauer | C17: 15 | D17: 25 | E17: Finance | F17: Lausanne | G17: F | H17: 1985 | I17: 9252 | J17: 3
B18: Robert Spear | C18: 8 | D18: 32 | E18: Sales | F18: Bern | G18: M | H18: 1988 | I18: 3270 | J18: 26
B19: Maria Tot | C19: 21 | D19: 19 | E19: Sales | F19: Geneva | G19: F | H19: 1988 | I19: 8257 | J19: 4 | L19: Bonus distribution
B20: Paul Hill | C20: 25 | D20: 15 | E20: Finance | F20: Zurich | G20: M | H20: 1988 | I20: 3023 | J20: 28 | L20: Matrix | M20: {=FREQUENCY($I$3:$I$40,L21:L26)} -> 10 | N20: ="<= "&L21 -> <= 3000
B21: Paul Garza | C21: 24 | D21: 16 | E21: Sales | F21: Bern | G21: M | H21: 1990 | I21: 7425 | J21: 8 | L21: 3000 | M21: 6 | N21: ="Entre "&L21+1&" et "&L22 -> Entre 3001 et 4000
B22: Natalie Porter | C22: 3 | D22: 36 | E22: Procurement | F22: Biel | G22: F | H22: 1990 | I22: 2539 | J22: 31 | L22: 4000 | M22: 7 | N22: ="Entre "&L22+1&" et "&L23 -> Entre 4001 et 5000
B23: Crystal Stucki | C23: 61 | D23: 1 | E23: Finance | F23: Zurich | G23: ND | H23: 1990 | I23: 4324 | J23: 21 | L23: 5000 | M23: 4 | N23: ="Entre "&L23+1&" et "&L24 -> Entre 5001 et 6500
B24: Paul Wells | C24: 19 | D24: 21 | E24: Sales | F24: Bern | G24: M | H24: 1996 | I24: 3152 | J24: 27 | L24: 6500 | M24: 0 | N24: ="Entre "&L24+1&" et "&L25 -> Entre 6501 et 7000
B25: Corinna Schmidt | C25: 16 | D25: 24 | E25: Procurement | F25: Biel | G25: F | H25: 1996 | I25: 4307 | J25: 22 | L25: 7000 | M25: 7 | N25: ="Entre "&L25+1&" et "&L26 -> Entre 7001 et 8000
B26: Robert Richardson | C26: 26 | D26: 14 | E26: Finance | F26: Lausanne | G26: M | H26: 1996 | I26: 6412 | J26: 12 | L26: 8000 | M26: 4 | N26: ="> "&L26 -> > 8000
B27: Wolfgang Ramjac | C27: 17 | D27: 23 | E27: Sales | F27: Geneva | G27: M | H27: 1999 | I27: 7238 | J27: 9 | M27: =_xlfn.FORMULATEXT(M20) -> =FREQUENCE($I$3:$I$40;L21:L26)
B28: Roger Mun | C28: 20 | D28: 20 | E28: Finance | F28: Zurich | G28: M | H28: 1999 | I28: 4434 | J28: 20
B29: Betina Klum | C29: 51 | D29: 3 | E29: Finance | F29: Lausanne | G29: F | H29: 1999 | I29: 4973 | J29: 16
B30: Kim Montreux | C30: 13 | D30: 27 | E30: Sales | F30: Bern | G30: M | H30: 2003 | I30: 7771 | J30: 5
B31: Robert Musser | C31: 30 | D31: 10 | E31: Procurement | F31: Biel | G31: M | H31: 2003 | I31: 7111 | J31: 11
B32: Daniela Schreiber | C32: 2 | D32: 37 | E32: Finance | F32: Lausanne | G32: F | H32: 2003 | I32: 9697 | J32: 2
B33: Stevie Bridge | C33: 7 | D33: 33 | E33: Sales | F33: Bern | G33: M | H33: 2005 | I33: 7723 | J33: 6
B34: Ann Withers | C34: 14 | D34: 26 | E34: Procurement | F34: Biel | G34: F | H34: 2005 | I34: 3496 | J34: 24
B35: Dan Ziegler | C35: 11 | D35: 29 | E35: Finance | F35: Lausanne | G35: M | H35: 2005 | I35: 1677 | J35: 34
B36: Robert Patrick | C36: 60 | D36: 2 | E36: Finance | F36: Lausanne | G36: M | H36: 2006 | I36: 2863 | J36: 29
B37: Lukas Arni | C37: 41 | D37: 7 | E37: Finance | F37: Lausanne | G37: M | H37: 2007 | I37: 920 | J37: 38
B38: Evelyne Schreiber | C38: 42 | D38: 6 | E38: Finance | F38: Lausanne | G38: F | H38: 2009 | I38: 2659 | J38: 30
B39: Robert Pattison | C39: 46 | D39: 4 | E39: Finance | F39: Lausanne | G39: M | H39: 2011 | I39: 5234 | J39: 15
B40: Peter Smith | C40: 32 | D40: 8 | E40: Finance | F40: Lausanne | G40: ND | H40: 2011 | I40: 4932 | J40: 18
D44: =_xlfn.FORMULATEXT($D$3) -> =EQUATION.RANG(C3:C40;$C$3:$C$40) | J44: =_xlfn.FORMULATEXT($J$3) -> =EQUATION.RANG(I3:I40;$I$3:$I$40)
